
# Pystats results

- benchmark: scimark
- fork: python
- ref: v3.13.0a2
- commit hash: 9c4347e
- commit date: 2023-11-22T12:20:24+01:00

## Execution counts

<details>
<summary> execution counts for all instructions </summary>

|Name | Count | Self | Cumulative | Miss ratio | 
|---|---:|---:|---:|---:|
| LOAD_FAST | 1,672,521,040 | 17.5% | 17.5% |  |
| LOAD_FAST_LOAD_FAST | 991,146,000 | 10.4% | 27.9% |  |
| STORE_FAST | 663,002,960 | 7.0% | 34.9% |  |
| BINARY_SUBSCR | 616,585,940 | 6.5% | 41.4% |  |
| LOAD_CONST | 554,057,840 | 5.8% | 47.2% |  |
| BINARY_OP_ADD_INT | 368,189,920 | 3.9% | 51.0% |  |
| POP_JUMP_IF_FALSE | 357,478,720 | 3.7% | 54.8% |  |
| LOAD_ATTR_INSTANCE_VALUE | 349,757,320 | 3.7% | 58.4% |  |
| SWAP | 325,758,720 | 3.4% | 61.9% |  |
| COPY | 325,750,400 | 3.4% | 65.3% |  |
| BINARY_OP_MULTIPLY_FLOAT | 318,709,020 | 3.3% | 68.6% |  |
| STORE_SUBSCR | 253,953,080 | 2.7% | 71.3% |  |
| COMPARE_OP_INT | 243,100,180 | 2.5% | 73.8% |  |
| BINARY_OP_ADD_FLOAT | 225,540,600 | 2.4% | 76.2% |  |
| RESUME_CHECK | 190,446,040 | 2.0% | 78.2% |  |
| BINARY_OP_SUBTRACT_FLOAT | 189,923,080 | 2.0% | 80.2% |  |
| FOR_ITER_RANGE | 189,168,980 | 2.0% | 82.2% |  |
| LOAD_GLOBAL_BUILTIN | 188,497,860 | 2.0% | 84.2% |  |
| JUMP_BACKWARD | 183,991,920 | 1.9% | 86.1% |  |
| RETURN_VALUE | 181,123,540 | 1.9% | 88.0% |  |
| BINARY_OP_MULTIPLY_INT | 140,367,200 | 1.5% | 89.5% |  |
| BINARY_SUBSCR_GETITEM | 118,050,820 | 1.2% | 90.7% |  |
| TO_BOOL_BOOL | 97,414,060 | 1.0% | 91.7% |  |
| JUMP_FORWARD | 94,194,080 | 1.0% | 92.7% |  |
| CALL_ISINSTANCE | 80,450,280 | 0.8% | 93.5% |  |
| BINARY_SUBSCR_LIST_INT | 80,435,080 | 0.8% | 94.4% |  |
| STORE_FAST_STORE_FAST | 63,871,120 | 0.7% | 95.1% |  |
| CALL_PY_EXACT_ARGS | 63,095,580 | 0.7% | 95.7% |  |
| LOAD_ATTR_METHOD_WITH_VALUES | 63,063,340 | 0.7% | 96.4% |  |
| BINARY_OP_SUBTRACT_INT | 55,505,320 | 0.6% | 97.0% |  |
| BUILD_TUPLE | 47,699,200 | 0.5% | 97.5% |  |
| UNPACK_SEQUENCE_TWO_TUPLE | 46,907,120 | 0.5% | 98.0% |  |
| BINARY_OP | 41,569,180 | 0.4% | 98.4% |  |
| STORE_ATTR_INSTANCE_VALUE | 33,929,600 | 0.4% | 98.7% |  |
| CALL_BUILTIN_CLASS | 27,192,860 | 0.3% | 99.0% |  |
| LOAD_ATTR_NONDESCRIPTOR_WITH_VALUES | 25,462,220 | 0.3% | 99.3% | 0.0% |
| COMPARE_OP | 16,977,860 | 0.2% | 99.5% |  |
| GET_ITER | 10,145,840 | 0.1% | 99.6% |  |
| RETURN_CONST | 8,523,520 | 0.1% | 99.7% |  |
| INTERPRETER_EXIT | 8,499,020 | 0.1% | 99.8% |  |
| POP_JUMP_IF_TRUE | 8,404,000 | 0.1% | 99.9% |  |
| COMPARE_OP_FLOAT | 8,395,960 | 0.1% | 99.9% |  |
| BINARY_SUBSCR_TUPLE_INT | 1,599,960 | 0.0% | 100.0% |  |
| POP_TOP | 825,120 | 0.0% | 100.0% |  |
| FOR_ITER_GEN | 800,060 | 0.0% | 100.0% |  |
| YIELD_VALUE | 800,000 | 0.0% | 100.0% |  |
| CALL_BUILTIN_O | 564,100 | 0.0% | 100.0% |  |
| LOAD_GLOBAL_MODULE | 290,080 | 0.0% | 100.0% |  |
| LOAD_ATTR_MODULE | 240,840 | 0.0% | 100.0% |  |
| LIST_APPEND | 179,840 | 0.0% | 100.0% |  |
| STORE_FAST_LOAD_FAST | 163,840 | 0.0% | 100.0% |  |
| PUSH_NULL | 162,080 | 0.0% | 100.0% |  |
| EXTENDED_ARG | 80,000 | 0.0% | 100.0% |  |
| CALL | 22,620 | 0.0% | 100.0% |  |
| BUILD_LIST | 17,440 | 0.0% | 100.0% |  |
| STORE_SUBSCR_LIST_INT | 15,180 | 0.0% | 100.0% |  |
| FOR_ITER | 9,500 | 0.0% | 100.0% |  |
| STORE_SLICE | 8,080 | 0.0% | 100.0% |  |
| LOAD_GLOBAL | 3,960 | 0.0% | 100.0% |  |
| LOAD_ATTR | 3,920 | 0.0% | 100.0% |  |
| STORE_ATTR | 1,440 | 0.0% | 100.0% |  |
| LOAD_DEREF | 1,200 | 0.0% | 100.0% |  |
| RESUME | 840 | 0.0% | 100.0% |  |
| CALL_FUNCTION_EX | 800 | 0.0% | 100.0% |  |
| NOP | 400 | 0.0% | 100.0% |  |
| CALL_INTRINSIC_1 | 400 | 0.0% | 100.0% |  |
| COPY_FREE_VARS | 400 | 0.0% | 100.0% |  |
| LIST_EXTEND | 400 | 0.0% | 100.0% |  |
| POP_JUMP_IF_NONE | 240 | 0.0% | 100.0% |  |
| LOAD_FAST_AND_CLEAR | 240 | 0.0% | 100.0% |  |
| TO_BOOL | 200 | 0.0% | 100.0% |  |
| EXIT_INIT_CHECK | 180 | 0.0% | 100.0% |  |
| CALL_ALLOC_AND_ENTER_INIT | 180 | 0.0% | 100.0% |  |
| UNPACK_SEQUENCE | 160 | 0.0% | 100.0% |  |
| BINARY_SLICE | 80 | 0.0% | 100.0% |  |
| END_FOR | 80 | 0.0% | 100.0% |  |
| RETURN_GENERATOR | 80 | 0.0% | 100.0% |  |


</details>

## Pair counts

<details>
<summary> Pair counts for top 100 pairs </summary>

|Pair | Count | Self | Cumulative | 
|---|---:|---:|---:|
| STORE_FAST LOAD_FAST_LOAD_FAST | 333,174,320 | 3.5% | 3.5% |
| LOAD_FAST LOAD_ATTR_INSTANCE_VALUE | 278,195,480 | 2.9% | 6.4% |
| LOAD_FAST_LOAD_FAST BINARY_SUBSCR | 253,144,080 | 2.7% | 9.1% |
| COMPARE_OP_INT POP_JUMP_IF_FALSE | 243,084,220 | 2.5% | 11.6% |
| POP_JUMP_IF_FALSE LOAD_FAST | 220,753,360 | 2.3% | 13.9% |
| LOAD_CONST BINARY_OP_ADD_INT | 203,314,400 | 2.1% | 16.1% |
| LOAD_FAST LOAD_FAST | 196,656,000 | 2.1% | 18.1% |
| LOAD_FAST_LOAD_FAST LOAD_CONST | 192,502,400 | 2.0% | 20.1% |
| LOAD_CONST LOAD_FAST | 190,314,880 | 2.0% | 22.1% |
| JUMP_BACKWARD FOR_ITER_RANGE | 179,023,320 | 1.9% | 24.0% |
| FOR_ITER_RANGE STORE_FAST | 178,859,500 | 1.9% | 25.9% |
| LOAD_ATTR_INSTANCE_VALUE LOAD_FAST | 177,444,900 | 1.9% | 27.8% |
| BINARY_SUBSCR LOAD_FAST | 172,428,180 | 1.8% | 29.6% |
| LOAD_FAST LOAD_CONST | 159,530,560 | 1.7% | 31.2% |
| LOAD_FAST BINARY_OP_MULTIPLY_FLOAT | 156,059,600 | 1.6% | 32.9% |
| STORE_FAST LOAD_FAST | 155,280,480 | 1.6% | 34.5% |
| LOAD_FAST BINARY_OP_ADD_INT | 148,427,000 | 1.6% | 36.1% |
| BINARY_SUBSCR LOAD_FAST_LOAD_FAST | 142,715,880 | 1.5% | 37.6% |
| STORE_SUBSCR LOAD_FAST_LOAD_FAST | 138,775,200 | 1.5% | 39.0% |
| BINARY_OP_MULTIPLY_FLOAT BINARY_OP_ADD_FLOAT | 120,563,000 | 1.3% | 40.3% |
| BINARY_SUBSCR_GETITEM RESUME_CHECK | 118,050,820 | 1.2% | 41.5% |
| COPY BINARY_SUBSCR | 116,776,000 | 1.2% | 42.7% |
| COPY COPY | 116,776,000 | 1.2% | 44.0% |
| SWAP STORE_SUBSCR | 116,776,000 | 1.2% | 45.2% |
| SWAP SWAP | 116,776,000 | 1.2% | 46.4% |
| LOAD_GLOBAL_BUILTIN LOAD_FAST | 98,020,120 | 1.0% | 47.4% |
| BINARY_OP_SUBTRACT_FLOAT LOAD_FAST_LOAD_FAST | 97,707,080 | 1.0% | 48.5% |
| TO_BOOL_BOOL POP_JUMP_IF_FALSE | 97,414,060 | 1.0% | 49.5% |
| BINARY_OP_ADD_FLOAT STORE_FAST | 96,775,960 | 1.0% | 50.5% |
| LOAD_FAST SWAP | 92,198,400 | 1.0% | 51.5% |
| POP_JUMP_IF_FALSE JUMP_FORWARD | 92,198,400 | 1.0% | 52.4% |
| SWAP COPY | 92,198,400 | 1.0% | 53.4% |
| COPY COMPARE_OP_INT | 92,198,320 | 1.0% | 54.4% |
| LOAD_ATTR_INSTANCE_VALUE COMPARE_OP_INT | 92,198,320 | 1.0% | 55.3% |
| BINARY_OP_ADD_INT BINARY_SUBSCR | 91,135,860 | 1.0% | 56.3% |
| BINARY_SUBSCR BINARY_OP_MULTIPLY_FLOAT | 90,267,920 | 0.9% | 57.2% |
| BINARY_SUBSCR STORE_FAST | 89,936,000 | 0.9% | 58.2% |
| LOAD_FAST BINARY_OP_SUBTRACT_FLOAT | 89,603,200 | 0.9% | 59.1% |
| STORE_SUBSCR JUMP_BACKWARD | 89,583,280 | 0.9% | 60.1% |
| STORE_FAST LOAD_CONST | 83,476,400 | 0.9% | 60.9% |
| BINARY_OP_MULTIPLY_FLOAT BINARY_OP_SUBTRACT_FLOAT | 83,355,800 | 0.9% | 61.8% |
| BINARY_OP_MULTIPLY_INT STORE_FAST | 82,084,020 | 0.9% | 62.7% |
| BINARY_OP_ADD_FLOAT SWAP | 81,919,920 | 0.9% | 63.5% |
| LOAD_FAST BINARY_OP_ADD_FLOAT | 81,919,840 | 0.9% | 64.4% |
| RESUME_CHECK LOAD_GLOBAL_BUILTIN | 80,450,480 | 0.8% | 65.2% |
| LOAD_FAST LOAD_GLOBAL_BUILTIN | 80,450,240 | 0.8% | 66.1% |
| LOAD_GLOBAL_BUILTIN CALL_ISINSTANCE | 80,450,240 | 0.8% | 66.9% |
| CALL_ISINSTANCE TO_BOOL_BOOL | 80,450,240 | 0.8% | 67.8% |
| BINARY_SUBSCR_LIST_INT RETURN_VALUE | 79,635,100 | 0.8% | 68.6% |
| LOAD_FAST BINARY_SUBSCR_LIST_INT | 79,635,080 | 0.8% | 69.4% |
| LOAD_FAST_LOAD_FAST BINARY_SUBSCR_GETITEM | 79,634,720 | 0.8% | 70.3% |
| RETURN_VALUE LOAD_FAST | 79,619,760 | 0.8% | 71.1% |
| STORE_FAST JUMP_BACKWARD | 78,505,440 | 0.8% | 71.9% |
| BINARY_OP_ADD_INT BINARY_OP_MULTIPLY_INT | 73,735,880 | 0.8% | 72.7% |
| LOAD_FAST_LOAD_FAST LOAD_ATTR_INSTANCE_VALUE | 71,561,160 | 0.8% | 73.5% |
| BINARY_OP_SUBTRACT_FLOAT STORE_FAST | 65,947,720 | 0.7% | 74.1% |
| BINARY_OP_MULTIPLY_FLOAT LOAD_FAST | 65,631,940 | 0.7% | 74.8% |
| BINARY_SUBSCR BINARY_SUBSCR | 64,157,600 | 0.7% | 75.5% |
| LOAD_FAST_LOAD_FAST LOAD_FAST_LOAD_FAST | 64,000,160 | 0.7% | 76.2% |
| CALL_PY_EXACT_ARGS RESUME_CHECK | 63,095,520 | 0.7% | 76.8% |
| RESUME_CHECK LOAD_FAST | 63,083,240 | 0.7% | 77.5% |
| LOAD_FAST LOAD_ATTR_METHOD_WITH_VALUES | 62,899,240 | 0.7% | 78.2% |
| LOAD_FAST_LOAD_FAST LOAD_FAST | 60,965,040 | 0.6% | 78.8% |
| BINARY_OP_ADD_INT STORE_SUBSCR | 52,975,880 | 0.6% | 79.4% |
| LOAD_FAST BINARY_SUBSCR | 52,955,960 | 0.6% | 79.9% |
| LOAD_FAST_LOAD_FAST COPY | 49,152,000 | 0.5% | 80.4% |
| JUMP_FORWARD LOAD_FAST_LOAD_FAST | 48,094,880 | 0.5% | 80.9% |
| LOAD_CONST BINARY_OP_SUBTRACT_INT | 47,401,080 | 0.5% | 81.4% |
| UNPACK_SEQUENCE_TWO_TUPLE STORE_FAST_STORE_FAST | 46,907,120 | 0.5% | 81.9% |
| LOAD_FAST_LOAD_FAST CALL_PY_EXACT_ARGS | 46,115,040 | 0.5% | 82.4% |
| RESUME_CHECK LOAD_CONST | 46,107,220 | 0.5% | 82.9% |
| JUMP_FORWARD LOAD_CONST | 46,099,200 | 0.5% | 83.4% |
| BINARY_OP_ADD_INT RETURN_VALUE | 46,099,180 | 0.5% | 83.9% |
| BINARY_OP_MULTIPLY_INT LOAD_FAST | 46,099,180 | 0.5% | 84.3% |
| LOAD_ATTR_INSTANCE_VALUE BINARY_OP_MULTIPLY_INT | 46,099,160 | 0.5% | 84.8% |
| LOAD_ATTR_METHOD_WITH_VALUES LOAD_FAST_LOAD_FAST | 46,099,160 | 0.5% | 85.3% |
| LOAD_FAST UNPACK_SEQUENCE_TWO_TUPLE | 46,099,120 | 0.5% | 85.8% |
| LOAD_FAST_LOAD_FAST STORE_SUBSCR | 44,943,200 | 0.5% | 86.3% |
| BINARY_OP STORE_FAST | 41,339,760 | 0.4% | 86.7% |
| BINARY_OP_ADD_INT COPY | 40,959,960 | 0.4% | 87.1% |
| BINARY_OP_ADD_INT LOAD_FAST | 40,878,920 | 0.4% | 87.6% |
| BINARY_OP_SUBTRACT_INT STORE_FAST | 40,043,840 | 0.4% | 88.0% |
| STORE_FAST_STORE_FAST LOAD_FAST | 39,216,000 | 0.4% | 88.4% |
| BINARY_SUBSCR RETURN_VALUE | 38,416,020 | 0.4% | 88.8% |
| RETURN_VALUE BINARY_SUBSCR | 38,416,000 | 0.4% | 89.2% |
| BUILD_TUPLE BINARY_SUBSCR_GETITEM | 38,415,800 | 0.4% | 89.6% |
| POP_JUMP_IF_FALSE LOAD_FAST_LOAD_FAST | 38,251,120 | 0.4% | 90.0% |
| LOAD_CONST COMPARE_OP_INT | 34,023,440 | 0.4% | 90.4% |
| LOAD_FAST_LOAD_FAST STORE_ATTR_INSTANCE_VALUE | 33,927,880 | 0.4% | 90.7% |
| STORE_ATTR_INSTANCE_VALUE LOAD_FAST | 33,927,760 | 0.4% | 91.1% |
| LOAD_CONST BINARY_OP | 32,762,200 | 0.3% | 91.4% |
| LOAD_FAST_LOAD_FAST BINARY_OP_MULTIPLY_FLOAT | 32,207,840 | 0.3% | 91.7% |
| LOAD_FAST BUILD_TUPLE | 31,532,800 | 0.3% | 92.1% |
| BINARY_OP_ADD_FLOAT LOAD_FAST_LOAD_FAST | 31,157,540 | 0.3% | 92.4% |
| LOAD_FAST COPY | 26,664,000 | 0.3% | 92.7% |
| BINARY_OP_SUBTRACT_FLOAT SWAP | 26,267,980 | 0.3% | 93.0% |
| LOAD_FAST_LOAD_FAST COMPARE_OP_INT | 24,655,680 | 0.3% | 93.2% |
| RETURN_VALUE BINARY_OP_ADD_FLOAT | 23,049,480 | 0.2% | 93.5% |
| LOAD_FAST STORE_SUBSCR | 22,223,960 | 0.2% | 93.7% |
| LOAD_FAST CALL_BUILTIN_CLASS | 17,641,000 | 0.2% | 93.9% |


</details>

## Predecessor/Successor Pairs

<details>
<summary> Top 5 predecessors and successors of each opcode </summary>

### BINARY_SLICE

<details>
<summary> Successors and predecessors for BINARY_SLICE </summary>

|Predecessors | Count | Percentage | 
|---|---:|---:|
| LOAD_CONST | 80 | 100.0% |

|Successors | Count | Percentage | 
|---|---:|---:|
| LOAD_FAST | 80 | 100.0% |


</details>

### STORE_SLICE

<details>
<summary> Successors and predecessors for STORE_SLICE </summary>

|Predecessors | Count | Percentage | 
|---|---:|---:|
| LOAD_CONST | 8,080 | 100.0% |

|Successors | Count | Percentage | 
|---|---:|---:|
| JUMP_BACKWARD | 8,000 | 99.0% |
| LOAD_FAST | 80 | 1.0% |


</details>

### CACHE

<details>
<summary> Successors and predecessors for CACHE </summary>

|Successors | Count | Percentage | 
|---|---:|---:|
| RESUME_CHECK | 8,498,820 | 100.0% |
| RESUME | 180 | 0.0% |
| POP_TOP | 20 | 0.0% |


</details>

### BINARY_SUBSCR

<details>
<summary> Successors and predecessors for BINARY_SUBSCR </summary>

|Predecessors | Count | Percentage | 
|---|---:|---:|
| LOAD_FAST_LOAD_FAST | 253,144,080 | 41.1% |
| COPY | 116,776,000 | 18.9% |
| BINARY_OP_ADD_INT | 91,135,860 | 14.8% |
| BINARY_SUBSCR | 64,157,600 | 10.4% |
| LOAD_FAST | 52,955,960 | 8.6% |

|Successors | Count | Percentage | 
|---|---:|---:|
| LOAD_FAST | 172,428,180 | 28.0% |
| LOAD_FAST_LOAD_FAST | 142,715,880 | 23.1% |
| BINARY_OP_MULTIPLY_FLOAT | 90,267,920 | 14.6% |
| STORE_FAST | 89,936,000 | 14.6% |
| BINARY_SUBSCR | 64,157,600 | 10.4% |


</details>

### GET_ITER

<details>
<summary> Successors and predecessors for GET_ITER </summary>

|Predecessors | Count | Percentage | 
|---|---:|---:|
| CALL_BUILTIN_CLASS | 10,144,760 | 100.0% |
| CALL | 600 | 0.0% |
| LOAD_FAST | 400 | 0.0% |
| RETURN_GENERATOR | 80 | 0.0% |

|Successors | Count | Percentage | 
|---|---:|---:|
| FOR_ITER_RANGE | 10,144,840 | 100.0% |
| FOR_ITER | 700 | 0.0% |
| LOAD_FAST_AND_CLEAR | 240 | 0.0% |
| FOR_ITER_GEN | 60 | 0.0% |


</details>

### INTERPRETER_EXIT

<details>
<summary> Successors and predecessors for INTERPRETER_EXIT </summary>

|Predecessors | Count | Percentage | 
|---|---:|---:|
| RETURN_CONST | 8,498,700 | 100.0% |
| RETURN_VALUE | 300 | 0.0% |
| YIELD_VALUE | 20 | 0.0% |


</details>

### NOP

<details>
<summary> Successors and predecessors for NOP </summary>

|Predecessors | Count | Percentage | 
|---|---:|---:|
| POP_TOP | 400 | 100.0% |

|Successors | Count | Percentage | 
|---|---:|---:|
| LOAD_DEREF | 400 | 100.0% |


</details>

### POP_TOP

<details>
<summary> Successors and predecessors for POP_TOP </summary>

|Predecessors | Count | Percentage | 
|---|---:|---:|
| RESUME_CHECK | 799,980 | 97.0% |
| RETURN_CONST | 24,560 | 3.0% |
| CALL | 400 | 0.0% |
| RETURN_VALUE | 80 | 0.0% |
| FOR_ITER_GEN | 60 | 0.0% |

|Successors | Count | Percentage | 
|---|---:|---:|
| JUMP_BACKWARD | 804,240 | 97.5% |
| LOAD_CONST | 12,240 | 1.5% |
| RETURN_CONST | 4,080 | 0.5% |
| LOAD_GLOBAL_MODULE | 4,000 | 0.5% |
| NOP | 400 | 0.0% |


</details>

### PUSH_NULL

<details>
<summary> Successors and predecessors for PUSH_NULL </summary>

|Predecessors | Count | Percentage | 
|---|---:|---:|
| LOAD_ATTR_MODULE | 160,860 | 99.2% |
| LOAD_DEREF | 800 | 0.5% |
| LOAD_ATTR | 340 | 0.2% |
| LOAD_FAST | 80 | 0.0% |

|Successors | Count | Percentage | 
|---|---:|---:|
| LOAD_FAST | 160,800 | 99.2% |
| CALL | 1,200 | 0.7% |
| LOAD_FAST_LOAD_FAST | 80 | 0.0% |


</details>

### RETURN_VALUE

<details>
<summary> Successors and predecessors for RETURN_VALUE </summary>

|Predecessors | Count | Percentage | 
|---|---:|---:|
| BINARY_SUBSCR_LIST_INT | 79,635,100 | 44.0% |
| BINARY_OP_ADD_INT | 46,099,180 | 25.5% |
| BINARY_SUBSCR | 38,416,020 | 21.2% |
| BINARY_OP_MULTIPLY_FLOAT | 16,963,840 | 9.4% |
| LOAD_FAST | 8,160 | 0.0% |

|Successors | Count | Percentage | 
|---|---:|---:|
| LOAD_FAST | 79,619,760 | 44.0% |
| BINARY_SUBSCR | 38,416,000 | 21.2% |
| BINARY_OP_ADD_FLOAT | 23,049,480 | 12.7% |
| STORE_FAST | 16,008,360 | 8.8% |
| LOAD_FAST_LOAD_FAST | 8,490,760 | 4.7% |


</details>

### STORE_SUBSCR

<details>
<summary> Successors and predecessors for STORE_SUBSCR </summary>

|Predecessors | Count | Percentage | 
|---|---:|---:|
| SWAP | 116,776,000 | 46.0% |
| BINARY_OP_ADD_INT | 52,975,880 | 20.9% |
| LOAD_FAST_LOAD_FAST | 44,943,200 | 17.7% |
| LOAD_FAST | 22,223,960 | 8.8% |
| BUILD_TUPLE | 8,483,200 | 3.3% |

|Successors | Count | Percentage | 
|---|---:|---:|
| LOAD_FAST_LOAD_FAST | 138,775,200 | 54.6% |
| JUMP_BACKWARD | 89,583,280 | 35.3% |
| LOAD_FAST | 17,043,840 | 6.7% |
| RETURN_CONST | 8,483,220 | 3.3% |
| STORE_SUBSCR | 67,440 | 0.0% |


</details>

### TO_BOOL

<details>
<summary> Successors and predecessors for TO_BOOL </summary>

|Predecessors | Count | Percentage | 
|---|---:|---:|
| LOAD_ATTR | 60 | 30.0% |
| LOAD_ATTR_INSTANCE_VALUE | 60 | 30.0% |
| CALL | 40 | 20.0% |
| CALL_ISINSTANCE | 40 | 20.0% |

|Successors | Count | Percentage | 
|---|---:|---:|
| POP_JUMP_IF_FALSE | 100 | 50.0% |
| TO_BOOL_BOOL | 100 | 50.0% |


</details>

### BINARY_OP

<details>
<summary> Successors and predecessors for BINARY_OP </summary>

|Predecessors | Count | Percentage | 
|---|---:|---:|
| LOAD_CONST | 32,762,200 | 78.8% |
| LOAD_ATTR_NONDESCRIPTOR_WITH_VALUES | 8,490,220 | 20.4% |
| LOAD_FAST | 109,880 | 0.3% |
| LOAD_FAST_LOAD_FAST | 88,800 | 0.2% |
| BINARY_OP_MULTIPLY_FLOAT | 80,180 | 0.2% |

|Successors | Count | Percentage | 
|---|---:|---:|
| STORE_FAST | 41,339,760 | 99.4% |
| CALL_BUILTIN_O | 79,960 | 0.2% |
| LOAD_GLOBAL_MODULE | 79,960 | 0.2% |
| BINARY_OP | 24,760 | 0.1% |
| LIST_APPEND | 16,000 | 0.0% |


</details>

### BUILD_LIST

<details>
<summary> Successors and predecessors for BUILD_LIST </summary>

|Predecessors | Count | Percentage | 
|---|---:|---:|
| LOAD_CONST | 16,800 | 96.3% |
| LOAD_FAST | 400 | 2.3% |
| SWAP | 240 | 1.4% |

|Successors | Count | Percentage | 
|---|---:|---:|
| CALL | 16,800 | 96.3% |
| LOAD_DEREF | 400 | 2.3% |
| SWAP | 240 | 1.4% |


</details>

### BUILD_TUPLE

<details>
<summary> Successors and predecessors for BUILD_TUPLE </summary>

|Predecessors | Count | Percentage | 
|---|---:|---:|
| LOAD_FAST | 31,532,800 | 66.1% |
| BINARY_OP_ADD_INT | 7,683,180 | 16.1% |
| BINARY_OP_SUBTRACT_INT | 7,683,180 | 16.1% |
| LOAD_FAST_LOAD_FAST | 800,000 | 1.7% |
| BINARY_OP | 40 | 0.0% |

|Successors | Count | Percentage | 
|---|---:|---:|
| BINARY_SUBSCR_GETITEM | 38,415,800 | 80.5% |
| STORE_SUBSCR | 8,483,200 | 17.8% |
| YIELD_VALUE | 800,000 | 1.7% |
| BINARY_SUBSCR | 200 | 0.0% |


</details>

### CALL

<details>
<summary> Successors and predecessors for CALL </summary>

|Predecessors | Count | Percentage | 
|---|---:|---:|
| BUILD_LIST | 16,800 | 74.3% |
| LOAD_FAST | 1,680 | 7.4% |
| PUSH_NULL | 1,200 | 5.3% |
| CALL | 900 | 4.0% |
| LOAD_FAST_LOAD_FAST | 560 | 2.5% |

|Successors | Count | Percentage | 
|---|---:|---:|
| LOAD_FAST | 16,900 | 74.7% |
| STORE_FAST | 1,240 | 5.5% |
| CALL | 900 | 4.0% |
| CALL_BUILTIN_CLASS | 740 | 3.3% |
| GET_ITER | 600 | 2.7% |


</details>

### CALL_FUNCTION_EX

<details>
<summary> Successors and predecessors for CALL_FUNCTION_EX </summary>

|Predecessors | Count | Percentage | 
|---|---:|---:|
| CALL_INTRINSIC_1 | 400 | 50.0% |
| LOAD_FAST | 400 | 50.0% |

|Successors | Count | Percentage | 
|---|---:|---:|
| COPY_FREE_VARS | 400 | 50.0% |
| RESUME_CHECK | 300 | 37.5% |
| RESUME | 100 | 12.5% |


</details>

### CALL_INTRINSIC_1

<details>
<summary> Successors and predecessors for CALL_INTRINSIC_1 </summary>

|Predecessors | Count | Percentage | 
|---|---:|---:|
| LIST_EXTEND | 400 | 100.0% |

|Successors | Count | Percentage | 
|---|---:|---:|
| CALL_FUNCTION_EX | 400 | 100.0% |


</details>

### COMPARE_OP

<details>
<summary> Successors and predecessors for COMPARE_OP </summary>

|Predecessors | Count | Percentage | 
|---|---:|---:|
| LOAD_CONST | 16,972,360 | 100.0% |
| COMPARE_OP | 4,860 | 0.0% |
| LOAD_FAST_LOAD_FAST | 360 | 0.0% |
| BINARY_OP | 80 | 0.0% |
| COPY | 80 | 0.0% |

|Successors | Count | Percentage | 
|---|---:|---:|
| POP_JUMP_IF_FALSE | 16,972,340 | 100.0% |
| COMPARE_OP | 4,860 | 0.0% |
| COMPARE_OP_INT | 540 | 0.0% |
| POP_JUMP_IF_TRUE | 60 | 0.0% |
| COMPARE_OP_FLOAT | 40 | 0.0% |


</details>

### COPY

<details>
<summary> Successors and predecessors for COPY </summary>

|Predecessors | Count | Percentage | 
|---|---:|---:|
| COPY | 116,776,000 | 35.8% |
| SWAP | 92,198,400 | 28.3% |
| LOAD_FAST_LOAD_FAST | 49,152,000 | 15.1% |
| BINARY_OP_ADD_INT | 40,959,960 | 12.6% |
| LOAD_FAST | 26,664,000 | 8.2% |

|Successors | Count | Percentage | 
|---|---:|---:|
| BINARY_SUBSCR | 116,776,000 | 35.8% |
| COPY | 116,776,000 | 35.8% |
| COMPARE_OP_INT | 92,198,320 | 28.3% |
| COMPARE_OP | 80 | 0.0% |


</details>

### COPY_FREE_VARS

<details>
<summary> Successors and predecessors for COPY_FREE_VARS </summary>

|Predecessors | Count | Percentage | 
|---|---:|---:|
| CALL_FUNCTION_EX | 400 | 100.0% |

|Successors | Count | Percentage | 
|---|---:|---:|
| RESUME_CHECK | 300 | 75.0% |
| RESUME | 100 | 25.0% |


</details>

### FOR_ITER

<details>
<summary> Successors and predecessors for FOR_ITER </summary>

|Predecessors | Count | Percentage | 
|---|---:|---:|
| JUMP_BACKWARD | 8,620 | 90.7% |
| GET_ITER | 700 | 7.4% |
| FOR_ITER | 140 | 1.5% |
| SWAP | 40 | 0.4% |

|Successors | Count | Percentage | 
|---|---:|---:|
| UNPACK_SEQUENCE_TWO_TUPLE | 7,960 | 83.8% |
| FOR_ITER_RANGE | 620 | 6.5% |
| STORE_FAST | 580 | 6.1% |
| FOR_ITER | 140 | 1.5% |
| RETURN_CONST | 80 | 0.8% |


</details>

### JUMP_BACKWARD

<details>
<summary> Successors and predecessors for JUMP_BACKWARD </summary>

|Predecessors | Count | Percentage | 
|---|---:|---:|
| STORE_SUBSCR | 89,583,280 | 48.7% |
| STORE_FAST | 78,505,440 | 42.7% |
| FOR_ITER_RANGE | 8,676,480 | 4.7% |
| POP_JUMP_IF_FALSE | 4,088,000 | 2.2% |
| POP_JUMP_IF_TRUE | 2,074,640 | 1.1% |

|Successors | Count | Percentage | 
|---|---:|---:|
| FOR_ITER_RANGE | 179,023,320 | 97.3% |
| LOAD_FAST_LOAD_FAST | 4,016,000 | 2.2% |
| FOR_ITER_GEN | 799,980 | 0.4% |
| LOAD_CONST | 72,000 | 0.0% |
| LOAD_FAST | 72,000 | 0.0% |


</details>

### JUMP_FORWARD

<details>
<summary> Successors and predecessors for JUMP_FORWARD </summary>

|Predecessors | Count | Percentage | 
|---|---:|---:|
| POP_JUMP_IF_FALSE | 92,198,400 | 97.9% |
| STORE_FAST | 1,995,680 | 2.1% |

|Successors | Count | Percentage | 
|---|---:|---:|
| LOAD_FAST_LOAD_FAST | 48,094,880 | 51.1% |
| LOAD_CONST | 46,099,200 | 48.9% |


</details>

### LIST_EXTEND

<details>
<summary> Successors and predecessors for LIST_EXTEND </summary>

|Predecessors | Count | Percentage | 
|---|---:|---:|
| LOAD_DEREF | 400 | 100.0% |

|Successors | Count | Percentage | 
|---|---:|---:|
| CALL_INTRINSIC_1 | 400 | 100.0% |


</details>

### LOAD_ATTR

<details>
<summary> Successors and predecessors for LOAD_ATTR </summary>

|Predecessors | Count | Percentage | 
|---|---:|---:|
| LOAD_FAST | 2,000 | 51.0% |
| LOAD_FAST_LOAD_FAST | 1,120 | 28.6% |
| LOAD_GLOBAL | 360 | 9.2% |
| LOAD_GLOBAL_MODULE | 360 | 9.2% |
| STORE_FAST_LOAD_FAST | 40 | 1.0% |

|Successors | Count | Percentage | 
|---|---:|---:|
| LOAD_ATTR_INSTANCE_VALUE | 680 | 17.3% |
| LOAD_ATTR_NONDESCRIPTOR_WITH_VALUES | 660 | 16.8% |
| LOAD_FAST | 540 | 13.8% |
| BINARY_OP | 460 | 11.7% |
| LOAD_ATTR_MODULE | 360 | 9.2% |


</details>

### LOAD_CONST

<details>
<summary> Successors and predecessors for LOAD_CONST </summary>

|Predecessors | Count | Percentage | 
|---|---:|---:|
| LOAD_FAST_LOAD_FAST | 192,502,400 | 34.7% |
| LOAD_FAST | 159,530,560 | 28.8% |
| STORE_FAST | 83,476,400 | 15.1% |
| RESUME_CHECK | 46,107,220 | 8.3% |
| JUMP_FORWARD | 46,099,200 | 8.3% |

|Successors | Count | Percentage | 
|---|---:|---:|
| BINARY_OP_ADD_INT | 203,314,400 | 36.7% |
| LOAD_FAST | 190,314,880 | 34.3% |
| BINARY_OP_SUBTRACT_INT | 47,401,080 | 8.6% |
| COMPARE_OP_INT | 34,023,440 | 6.1% |
| BINARY_OP | 32,762,200 | 5.9% |


</details>

### LOAD_DEREF

<details>
<summary> Successors and predecessors for LOAD_DEREF </summary>

|Predecessors | Count | Percentage | 
|---|---:|---:|
| NOP | 400 | 33.3% |
| BUILD_LIST | 400 | 33.3% |
| RESUME_CHECK | 300 | 25.0% |
| RESUME | 100 | 8.3% |

|Successors | Count | Percentage | 
|---|---:|---:|
| PUSH_NULL | 800 | 66.7% |
| LIST_EXTEND | 400 | 33.3% |


</details>

### LOAD_FAST

<details>
<summary> Successors and predecessors for LOAD_FAST </summary>

|Predecessors | Count | Percentage | 
|---|---:|---:|
| POP_JUMP_IF_FALSE | 220,753,360 | 13.2% |
| LOAD_FAST | 196,656,000 | 11.8% |
| LOAD_CONST | 190,314,880 | 11.4% |
| LOAD_ATTR_INSTANCE_VALUE | 177,444,900 | 10.6% |
| BINARY_SUBSCR | 172,428,180 | 10.3% |

|Successors | Count | Percentage | 
|---|---:|---:|
| LOAD_ATTR_INSTANCE_VALUE | 278,195,480 | 16.6% |
| LOAD_FAST | 196,656,000 | 11.8% |
| LOAD_CONST | 159,530,560 | 9.5% |
| BINARY_OP_MULTIPLY_FLOAT | 156,059,600 | 9.3% |
| BINARY_OP_ADD_INT | 148,427,000 | 8.9% |


</details>

### LOAD_FAST_LOAD_FAST

<details>
<summary> Successors and predecessors for LOAD_FAST_LOAD_FAST </summary>

|Predecessors | Count | Percentage | 
|---|---:|---:|
| STORE_FAST | 333,174,320 | 33.6% |
| BINARY_SUBSCR | 142,715,880 | 14.4% |
| STORE_SUBSCR | 138,775,200 | 14.0% |
| BINARY_OP_SUBTRACT_FLOAT | 97,707,080 | 9.9% |
| LOAD_FAST_LOAD_FAST | 64,000,160 | 6.5% |

|Successors | Count | Percentage | 
|---|---:|---:|
| BINARY_SUBSCR | 253,144,080 | 25.5% |
| LOAD_CONST | 192,502,400 | 19.4% |
| BINARY_SUBSCR_GETITEM | 79,634,720 | 8.0% |
| LOAD_ATTR_INSTANCE_VALUE | 71,561,160 | 7.2% |
| LOAD_FAST_LOAD_FAST | 64,000,160 | 6.5% |


</details>

### LOAD_GLOBAL

<details>
<summary> Successors and predecessors for LOAD_GLOBAL </summary>

|Predecessors | Count | Percentage | 
|---|---:|---:|
| STORE_FAST | 1,880 | 47.5% |
| FOR_ITER_RANGE | 320 | 8.1% |
| RESUME | 280 | 7.1% |
| RESUME_CHECK | 280 | 7.1% |
| RETURN_VALUE | 200 | 5.1% |

|Successors | Count | Percentage | 
|---|---:|---:|
| LOAD_GLOBAL_BUILTIN | 1,020 | 25.8% |
| LOAD_GLOBAL_MODULE | 960 | 24.2% |
| LOAD_FAST | 740 | 18.7% |
| LOAD_CONST | 500 | 12.6% |
| LOAD_ATTR | 360 | 9.1% |


</details>

### POP_JUMP_IF_FALSE

<details>
<summary> Successors and predecessors for POP_JUMP_IF_FALSE </summary>

|Predecessors | Count | Percentage | 
|---|---:|---:|
| COMPARE_OP_INT | 243,084,220 | 68.0% |
| TO_BOOL_BOOL | 97,414,060 | 27.3% |
| COMPARE_OP | 16,972,340 | 4.7% |
| EXTENDED_ARG | 8,000 | 0.0% |
| TO_BOOL | 100 | 0.0% |

|Successors | Count | Percentage | 
|---|---:|---:|
| LOAD_FAST | 220,753,360 | 61.8% |
| JUMP_FORWARD | 92,198,400 | 25.8% |
| LOAD_FAST_LOAD_FAST | 38,251,120 | 10.7% |
| JUMP_BACKWARD | 4,088,000 | 1.1% |
| LOAD_CONST | 2,015,840 | 0.6% |


</details>

### POP_JUMP_IF_NONE

<details>
<summary> Successors and predecessors for POP_JUMP_IF_NONE </summary>

|Predecessors | Count | Percentage | 
|---|---:|---:|
| LOAD_FAST | 240 | 100.0% |

|Successors | Count | Percentage | 
|---|---:|---:|
| RETURN_CONST | 240 | 100.0% |


</details>

### POP_JUMP_IF_TRUE

<details>
<summary> Successors and predecessors for POP_JUMP_IF_TRUE </summary>

|Predecessors | Count | Percentage | 
|---|---:|---:|
| COMPARE_OP_FLOAT | 8,395,960 | 99.9% |
| COMPARE_OP_INT | 7,980 | 0.1% |
| COMPARE_OP | 60 | 0.0% |

|Successors | Count | Percentage | 
|---|---:|---:|
| LOAD_FAST | 6,321,440 | 75.2% |
| JUMP_BACKWARD | 2,074,640 | 24.7% |
| LOAD_GLOBAL_BUILTIN | 7,880 | 0.1% |
| LOAD_GLOBAL | 40 | 0.0% |


</details>

### RETURN_CONST

<details>
<summary> Successors and predecessors for RETURN_CONST </summary>

|Predecessors | Count | Percentage | 
|---|---:|---:|
| STORE_SUBSCR | 8,483,220 | 99.5% |
| STORE_SUBSCR_LIST_INT | 15,180 | 0.2% |
| FOR_ITER_RANGE | 12,240 | 0.1% |
| POP_JUMP_IF_FALSE | 8,000 | 0.1% |
| POP_TOP | 4,080 | 0.0% |

|Successors | Count | Percentage | 
|---|---:|---:|
| INTERPRETER_EXIT | 8,498,700 | 99.7% |
| POP_TOP | 24,560 | 0.3% |
| EXIT_INIT_CHECK | 180 | 0.0% |
| END_FOR | 80 | 0.0% |


</details>

### STORE_ATTR

<details>
<summary> Successors and predecessors for STORE_ATTR </summary>

|Predecessors | Count | Percentage | 
|---|---:|---:|
| LOAD_FAST | 920 | 63.9% |
| LOAD_FAST_LOAD_FAST | 520 | 36.1% |

|Successors | Count | Percentage | 
|---|---:|---:|
| STORE_ATTR_INSTANCE_VALUE | 720 | 50.0% |
| LOAD_CONST | 240 | 16.7% |
| LOAD_FAST | 160 | 11.1% |
| LOAD_GLOBAL | 160 | 11.1% |
| RETURN_CONST | 120 | 8.3% |


</details>

### STORE_FAST

<details>
<summary> Successors and predecessors for STORE_FAST </summary>

|Predecessors | Count | Percentage | 
|---|---:|---:|
| FOR_ITER_RANGE | 178,859,500 | 27.0% |
| BINARY_OP_ADD_FLOAT | 96,775,960 | 14.6% |
| BINARY_SUBSCR | 89,936,000 | 13.6% |
| BINARY_OP_MULTIPLY_INT | 82,084,020 | 12.4% |
| BINARY_OP_SUBTRACT_FLOAT | 65,947,720 | 9.9% |

|Successors | Count | Percentage | 
|---|---:|---:|
| LOAD_FAST_LOAD_FAST | 333,174,320 | 50.3% |
| LOAD_FAST | 155,280,480 | 23.4% |
| LOAD_CONST | 83,476,400 | 12.6% |
| JUMP_BACKWARD | 78,505,440 | 11.8% |
| LOAD_GLOBAL_BUILTIN | 10,384,120 | 1.6% |


</details>

### STORE_FAST_STORE_FAST

<details>
<summary> Successors and predecessors for STORE_FAST_STORE_FAST </summary>

|Predecessors | Count | Percentage | 
|---|---:|---:|
| UNPACK_SEQUENCE_TWO_TUPLE | 46,907,120 | 73.4% |
| LOAD_ATTR_INSTANCE_VALUE | 16,963,840 | 26.6% |
| LOAD_ATTR | 80 | 0.0% |
| UNPACK_SEQUENCE | 80 | 0.0% |

|Successors | Count | Percentage | 
|---|---:|---:|
| LOAD_FAST | 39,216,000 | 61.4% |
| STORE_FAST | 16,963,840 | 26.6% |
| LOAD_FAST_LOAD_FAST | 7,691,200 | 12.0% |
| LOAD_GLOBAL | 40 | 0.0% |
| LOAD_GLOBAL_BUILTIN | 40 | 0.0% |


</details>

### SWAP

<details>
<summary> Successors and predecessors for SWAP </summary>

|Predecessors | Count | Percentage | 
|---|---:|---:|
| SWAP | 116,776,000 | 35.8% |
| LOAD_FAST | 92,198,400 | 28.3% |
| BINARY_OP_ADD_FLOAT | 81,919,920 | 25.1% |
| BINARY_OP_SUBTRACT_FLOAT | 26,267,980 | 8.1% |
| BINARY_OP_MULTIPLY_FLOAT | 8,587,960 | 2.6% |

|Successors | Count | Percentage | 
|---|---:|---:|
| STORE_SUBSCR | 116,776,000 | 35.8% |
| SWAP | 116,776,000 | 35.8% |
| COPY | 92,198,400 | 28.3% |
| LOAD_FAST_LOAD_FAST | 7,600 | 0.0% |
| BUILD_LIST | 240 | 0.0% |


</details>

### UNPACK_SEQUENCE

<details>
<summary> Successors and predecessors for UNPACK_SEQUENCE </summary>

|Predecessors | Count | Percentage | 
|---|---:|---:|
| LOAD_FAST | 80 | 50.0% |
| FOR_ITER | 60 | 37.5% |
| YIELD_VALUE | 20 | 12.5% |

|Successors | Count | Percentage | 
|---|---:|---:|
| STORE_FAST_STORE_FAST | 80 | 50.0% |
| UNPACK_SEQUENCE_TWO_TUPLE | 80 | 50.0% |


</details>

### RESUME

<details>
<summary> Successors and predecessors for RESUME </summary>

|Predecessors | Count | Percentage | 
|---|---:|---:|
| CALL | 420 | 50.0% |
| CACHE | 180 | 21.4% |
| CALL_FUNCTION_EX | 100 | 11.9% |
| COPY_FREE_VARS | 100 | 11.9% |
| POP_TOP | 20 | 2.4% |

|Successors | Count | Percentage | 
|---|---:|---:|
| LOAD_FAST | 280 | 33.3% |
| LOAD_GLOBAL | 280 | 33.3% |
| LOAD_DEREF | 100 | 11.9% |
| LOAD_FAST_LOAD_FAST | 100 | 11.9% |
| LOAD_CONST | 60 | 7.1% |


</details>

### BINARY_OP_ADD_FLOAT

<details>
<summary> Successors and predecessors for BINARY_OP_ADD_FLOAT </summary>

|Predecessors | Count | Percentage | 
|---|---:|---:|
| BINARY_OP_MULTIPLY_FLOAT | 120,563,000 | 53.5% |
| LOAD_FAST | 81,919,840 | 36.3% |
| RETURN_VALUE | 23,049,480 | 10.2% |
| BINARY_OP | 8,280 | 0.0% |

|Successors | Count | Percentage | 
|---|---:|---:|
| STORE_FAST | 96,775,960 | 42.9% |
| SWAP | 81,919,920 | 36.3% |
| LOAD_FAST_LOAD_FAST | 31,157,540 | 13.8% |
| LOAD_CONST | 7,999,980 | 3.5% |
| BINARY_OP_MULTIPLY_FLOAT | 7,683,160 | 3.4% |


</details>

### BINARY_OP_ADD_INT

<details>
<summary> Successors and predecessors for BINARY_OP_ADD_INT </summary>

|Predecessors | Count | Percentage | 
|---|---:|---:|
| LOAD_CONST | 203,314,400 | 55.2% |
| LOAD_FAST | 148,427,000 | 40.3% |
| LOAD_FAST_LOAD_FAST | 16,447,880 | 4.5% |
| BINARY_OP | 640 | 0.0% |

|Successors | Count | Percentage | 
|---|---:|---:|
| BINARY_SUBSCR | 91,135,860 | 24.8% |
| BINARY_OP_MULTIPLY_INT | 73,735,880 | 20.0% |
| STORE_SUBSCR | 52,975,880 | 14.4% |
| RETURN_VALUE | 46,099,180 | 12.5% |
| COPY | 40,959,960 | 11.1% |


</details>

### BINARY_OP_MULTIPLY_FLOAT

<details>
<summary> Successors and predecessors for BINARY_OP_MULTIPLY_FLOAT </summary>

|Predecessors | Count | Percentage | 
|---|---:|---:|
| LOAD_FAST | 156,059,600 | 49.0% |
| BINARY_SUBSCR | 90,267,920 | 28.3% |
| LOAD_FAST_LOAD_FAST | 32,207,840 | 10.1% |
| CALL_BUILTIN_CLASS | 17,043,680 | 5.3% |
| LOAD_CONST | 7,683,200 | 2.4% |

|Successors | Count | Percentage | 
|---|---:|---:|
| BINARY_OP_ADD_FLOAT | 120,563,000 | 37.8% |
| BINARY_OP_SUBTRACT_FLOAT | 83,355,800 | 26.2% |
| LOAD_FAST | 65,631,940 | 20.6% |
| RETURN_VALUE | 16,963,840 | 5.3% |
| LOAD_FAST_LOAD_FAST | 15,683,160 | 4.9% |


</details>

### BINARY_OP_MULTIPLY_INT

<details>
<summary> Successors and predecessors for BINARY_OP_MULTIPLY_INT </summary>

|Predecessors | Count | Percentage | 
|---|---:|---:|
| BINARY_OP_ADD_INT | 73,735,880 | 52.5% |
| LOAD_ATTR_INSTANCE_VALUE | 46,099,160 | 32.8% |
| LOAD_FAST | 16,367,920 | 11.7% |
| LOAD_FAST_LOAD_FAST | 4,004,000 | 2.9% |
| LOAD_CONST | 159,920 | 0.1% |

|Successors | Count | Percentage | 
|---|---:|---:|
| STORE_FAST | 82,084,020 | 58.5% |
| LOAD_FAST | 46,099,180 | 32.8% |
| CALL_BUILTIN_CLASS | 8,183,920 | 5.8% |
| LOAD_FAST_LOAD_FAST | 3,999,980 | 2.8% |
| BINARY_OP | 60 | 0.0% |


</details>

### BINARY_OP_SUBTRACT_FLOAT

<details>
<summary> Successors and predecessors for BINARY_OP_SUBTRACT_FLOAT </summary>

|Predecessors | Count | Percentage | 
|---|---:|---:|
| LOAD_FAST | 89,603,200 | 47.2% |
| BINARY_OP_MULTIPLY_FLOAT | 83,355,800 | 43.9% |
| BINARY_SUBSCR | 16,963,720 | 8.9% |
| BINARY_OP | 360 | 0.0% |

|Successors | Count | Percentage | 
|---|---:|---:|
| LOAD_FAST_LOAD_FAST | 97,707,080 | 51.4% |
| STORE_FAST | 65,947,720 | 34.7% |
| SWAP | 26,267,980 | 13.8% |
| RETURN_VALUE | 300 | 0.0% |


</details>

### BINARY_OP_SUBTRACT_INT

<details>
<summary> Successors and predecessors for BINARY_OP_SUBTRACT_INT </summary>

|Predecessors | Count | Percentage | 
|---|---:|---:|
| LOAD_CONST | 47,401,080 | 85.4% |
| LOAD_FAST_LOAD_FAST | 8,103,960 | 14.6% |
| BINARY_OP | 280 | 0.0% |

|Successors | Count | Percentage | 
|---|---:|---:|
| STORE_FAST | 40,043,840 | 72.1% |
| BUILD_TUPLE | 7,683,180 | 13.8% |
| LOAD_FAST | 7,683,180 | 13.8% |
| CALL_BUILTIN_CLASS | 79,120 | 0.1% |
| COMPARE_OP_INT | 15,920 | 0.0% |


</details>

### BINARY_SUBSCR_GETITEM

<details>
<summary> Successors and predecessors for BINARY_SUBSCR_GETITEM </summary>

|Predecessors | Count | Percentage | 
|---|---:|---:|
| LOAD_FAST_LOAD_FAST | 79,634,720 | 67.5% |
| BUILD_TUPLE | 38,415,800 | 32.5% |
| BINARY_SUBSCR | 300 | 0.0% |

|Successors | Count | Percentage | 
|---|---:|---:|
| RESUME_CHECK | 118,050,820 | 100.0% |


</details>

### CALL_BUILTIN_CLASS

<details>
<summary> Successors and predecessors for CALL_BUILTIN_CLASS </summary>

|Predecessors | Count | Percentage | 
|---|---:|---:|
| LOAD_FAST | 17,641,000 | 64.9% |
| BINARY_OP_MULTIPLY_INT | 8,183,920 | 30.1% |
| BINARY_SUBSCR | 1,279,960 | 4.7% |
| BINARY_OP_SUBTRACT_INT | 79,120 | 0.3% |
| LOAD_ATTR_INSTANCE_VALUE | 8,000 | 0.0% |

|Successors | Count | Percentage | 
|---|---:|---:|
| BINARY_OP_MULTIPLY_FLOAT | 17,043,680 | 62.7% |
| GET_ITER | 10,144,760 | 37.3% |
| BINARY_OP | 4,060 | 0.0% |
| STORE_FAST | 300 | 0.0% |
| LOAD_FAST | 60 | 0.0% |


</details>

### CALL_PY_EXACT_ARGS

<details>
<summary> Successors and predecessors for CALL_PY_EXACT_ARGS </summary>

|Predecessors | Count | Percentage | 
|---|---:|---:|
| LOAD_FAST_LOAD_FAST | 46,115,040 | 73.1% |
| LOAD_ATTR_METHOD_WITH_VALUES | 16,963,720 | 26.9% |
| LOAD_FAST | 8,360 | 0.0% |
| LOAD_CONST | 7,920 | 0.0% |
| CALL | 540 | 0.0% |

|Successors | Count | Percentage | 
|---|---:|---:|
| RESUME_CHECK | 63,095,520 | 100.0% |
| RETURN_GENERATOR | 60 | 0.0% |


</details>

### COMPARE_OP_INT

<details>
<summary> Successors and predecessors for COMPARE_OP_INT </summary>

|Predecessors | Count | Percentage | 
|---|---:|---:|
| COPY | 92,198,320 | 37.9% |
| LOAD_ATTR_INSTANCE_VALUE | 92,198,320 | 37.9% |
| LOAD_CONST | 34,023,440 | 14.0% |
| LOAD_FAST_LOAD_FAST | 24,655,680 | 10.1% |
| BINARY_OP_SUBTRACT_INT | 15,920 | 0.0% |

|Successors | Count | Percentage | 
|---|---:|---:|
| POP_JUMP_IF_FALSE | 243,084,220 | 100.0% |
| EXTENDED_ARG | 7,980 | 0.0% |
| POP_JUMP_IF_TRUE | 7,980 | 0.0% |


</details>

### FOR_ITER_RANGE

<details>
<summary> Successors and predecessors for FOR_ITER_RANGE </summary>

|Predecessors | Count | Percentage | 
|---|---:|---:|
| JUMP_BACKWARD | 179,023,320 | 94.6% |
| GET_ITER | 10,144,840 | 5.4% |
| FOR_ITER | 620 | 0.0% |
| SWAP | 200 | 0.0% |

|Successors | Count | Percentage | 
|---|---:|---:|
| STORE_FAST | 178,859,500 | 94.6% |
| JUMP_BACKWARD | 8,676,480 | 4.6% |
| LOAD_FAST_LOAD_FAST | 1,295,920 | 0.7% |
| STORE_FAST_LOAD_FAST | 163,820 | 0.1% |
| LOAD_GLOBAL_BUILTIN | 80,000 | 0.0% |


</details>

### LOAD_ATTR_INSTANCE_VALUE

<details>
<summary> Successors and predecessors for LOAD_ATTR_INSTANCE_VALUE </summary>

|Predecessors | Count | Percentage | 
|---|---:|---:|
| LOAD_FAST | 278,195,480 | 79.5% |
| LOAD_FAST_LOAD_FAST | 71,561,160 | 20.5% |
| LOAD_ATTR | 680 | 0.0% |

|Successors | Count | Percentage | 
|---|---:|---:|
| LOAD_FAST | 177,444,900 | 50.7% |
| COMPARE_OP_INT | 92,198,320 | 26.4% |
| BINARY_OP_MULTIPLY_INT | 46,099,160 | 13.2% |
| STORE_FAST_STORE_FAST | 16,963,840 | 4.9% |
| TO_BOOL_BOOL | 16,963,720 | 4.9% |


</details>

### LOAD_ATTR_METHOD_WITH_VALUES

<details>
<summary> Successors and predecessors for LOAD_ATTR_METHOD_WITH_VALUES </summary>

|Predecessors | Count | Percentage | 
|---|---:|---:|
| LOAD_FAST | 62,899,240 | 99.7% |
| STORE_FAST_LOAD_FAST | 163,800 | 0.3% |
| LOAD_ATTR | 260 | 0.0% |
| RETURN_VALUE | 40 | 0.0% |

|Successors | Count | Percentage | 
|---|---:|---:|
| LOAD_FAST_LOAD_FAST | 46,099,160 | 73.1% |
| CALL_PY_EXACT_ARGS | 16,963,720 | 26.9% |
| LOAD_FAST | 300 | 0.0% |
| CALL | 100 | 0.0% |
| LOAD_GLOBAL_MODULE | 40 | 0.0% |


</details>

### LOAD_ATTR_MODULE

<details>
<summary> Successors and predecessors for LOAD_ATTR_MODULE </summary>

|Predecessors | Count | Percentage | 
|---|---:|---:|
| LOAD_GLOBAL_MODULE | 240,480 | 99.9% |
| LOAD_ATTR | 360 | 0.1% |

|Successors | Count | Percentage | 
|---|---:|---:|
| PUSH_NULL | 160,860 | 66.8% |
| BINARY_OP_MULTIPLY_FLOAT | 79,960 | 33.2% |
| BINARY_OP | 20 | 0.0% |


</details>

### LOAD_GLOBAL_BUILTIN

<details>
<summary> Successors and predecessors for LOAD_GLOBAL_BUILTIN </summary>

|Predecessors | Count | Percentage | 
|---|---:|---:|
| RESUME_CHECK | 80,450,480 | 42.7% |
| LOAD_FAST | 80,450,240 | 42.7% |
| LOAD_ATTR_NONDESCRIPTOR_WITH_VALUES | 16,963,720 | 9.0% |
| STORE_FAST | 10,384,120 | 5.5% |
| LOAD_CONST | 83,960 | 0.0% |

|Successors | Count | Percentage | 
|---|---:|---:|
| LOAD_FAST | 98,020,120 | 52.0% |
| CALL_ISINSTANCE | 80,450,240 | 42.7% |
| LOAD_CONST | 8,343,280 | 4.4% |
| LOAD_FAST_LOAD_FAST | 1,684,180 | 0.9% |
| CALL | 40 | 0.0% |


</details>

### LOAD_GLOBAL_MODULE

<details>
<summary> Successors and predecessors for LOAD_GLOBAL_MODULE </summary>

|Predecessors | Count | Percentage | 
|---|---:|---:|
| STORE_FAST | 184,560 | 63.6% |
| BINARY_OP | 79,960 | 27.6% |
| POP_JUMP_IF_FALSE | 15,920 | 5.5% |
| RESUME_CHECK | 4,160 | 1.4% |
| POP_TOP | 4,000 | 1.4% |

|Successors | Count | Percentage | 
|---|---:|---:|
| LOAD_ATTR_MODULE | 240,480 | 82.9% |
| LOAD_FAST_LOAD_FAST | 24,200 | 8.3% |
| LOAD_CONST | 16,940 | 5.8% |
| LOAD_FAST | 8,100 | 2.8% |
| LOAD_ATTR | 360 | 0.1% |


</details>

### RESUME_CHECK

<details>
<summary> Successors and predecessors for RESUME_CHECK </summary>

|Predecessors | Count | Percentage | 
|---|---:|---:|
| BINARY_SUBSCR_GETITEM | 118,050,820 | 62.0% |
| CALL_PY_EXACT_ARGS | 63,095,520 | 33.1% |
| CACHE | 8,498,820 | 4.5% |
| FOR_ITER_GEN | 799,980 | 0.4% |
| CALL_FUNCTION_EX | 300 | 0.0% |

|Successors | Count | Percentage | 
|---|---:|---:|
| LOAD_GLOBAL_BUILTIN | 80,450,480 | 42.2% |
| LOAD_FAST | 63,083,240 | 33.1% |
| LOAD_CONST | 46,107,220 | 24.2% |
| POP_TOP | 799,980 | 0.4% |
| LOAD_GLOBAL_MODULE | 4,160 | 0.0% |


</details>

### STORE_ATTR_INSTANCE_VALUE

<details>
<summary> Successors and predecessors for STORE_ATTR_INSTANCE_VALUE </summary>

|Predecessors | Count | Percentage | 
|---|---:|---:|
| LOAD_FAST_LOAD_FAST | 33,927,880 | 100.0% |
| LOAD_FAST | 1,000 | 0.0% |
| STORE_ATTR | 720 | 0.0% |

|Successors | Count | Percentage | 
|---|---:|---:|
| LOAD_FAST | 33,927,760 | 100.0% |
| LOAD_CONST | 720 | 0.0% |
| RETURN_CONST | 360 | 0.0% |
| LOAD_GLOBAL_BUILTIN | 360 | 0.0% |
| LOAD_FAST_LOAD_FAST | 200 | 0.0% |


</details>

### UNPACK_SEQUENCE_TWO_TUPLE

<details>
<summary> Successors and predecessors for UNPACK_SEQUENCE_TWO_TUPLE </summary>

|Predecessors | Count | Percentage | 
|---|---:|---:|
| LOAD_FAST | 46,099,120 | 98.3% |
| YIELD_VALUE | 799,960 | 1.7% |
| FOR_ITER | 7,960 | 0.0% |
| UNPACK_SEQUENCE | 80 | 0.0% |

|Successors | Count | Percentage | 
|---|---:|---:|
| STORE_FAST_STORE_FAST | 46,907,120 | 100.0% |


</details>

### EXIT_INIT_CHECK

<details>
<summary> Successors and predecessors for EXIT_INIT_CHECK </summary>

|Predecessors | Count | Percentage | 
|---|---:|---:|
| RETURN_CONST | 180 | 100.0% |

|Successors | Count | Percentage | 
|---|---:|---:|
| RETURN_VALUE | 180 | 100.0% |


</details>

### EXTENDED_ARG

<details>
<summary> Successors and predecessors for EXTENDED_ARG </summary>

|Predecessors | Count | Percentage | 
|---|---:|---:|
| POP_JUMP_IF_FALSE | 72,000 | 90.0% |
| COMPARE_OP_INT | 7,980 | 10.0% |
| COMPARE_OP | 20 | 0.0% |

|Successors | Count | Percentage | 
|---|---:|---:|
| JUMP_BACKWARD | 72,000 | 90.0% |
| POP_JUMP_IF_FALSE | 8,000 | 10.0% |


</details>

### LIST_APPEND

<details>
<summary> Successors and predecessors for LIST_APPEND </summary>

|Predecessors | Count | Percentage | 
|---|---:|---:|
| RETURN_VALUE | 163,840 | 91.1% |
| BINARY_OP | 16,000 | 8.9% |

|Successors | Count | Percentage | 
|---|---:|---:|
| JUMP_BACKWARD | 179,840 | 100.0% |


</details>

### LOAD_FAST_AND_CLEAR

<details>
<summary> Successors and predecessors for LOAD_FAST_AND_CLEAR </summary>

|Predecessors | Count | Percentage | 
|---|---:|---:|
| GET_ITER | 240 | 100.0% |

|Successors | Count | Percentage | 
|---|---:|---:|
| SWAP | 240 | 100.0% |


</details>

### STORE_FAST_LOAD_FAST

<details>
<summary> Successors and predecessors for STORE_FAST_LOAD_FAST </summary>

|Predecessors | Count | Percentage | 
|---|---:|---:|
| FOR_ITER_RANGE | 163,820 | 100.0% |
| FOR_ITER | 20 | 0.0% |

|Successors | Count | Percentage | 
|---|---:|---:|
| LOAD_ATTR_METHOD_WITH_VALUES | 163,800 | 100.0% |
| LOAD_ATTR | 40 | 0.0% |


</details>

### CALL_ALLOC_AND_ENTER_INIT

<details>
<summary> Successors and predecessors for CALL_ALLOC_AND_ENTER_INIT </summary>

|Predecessors | Count | Percentage | 
|---|---:|---:|
| LOAD_CONST | 120 | 66.7% |
| CALL | 60 | 33.3% |

|Successors | Count | Percentage | 
|---|---:|---:|
| RESUME_CHECK | 180 | 100.0% |


</details>

### CALL_BUILTIN_O

<details>
<summary> Successors and predecessors for CALL_BUILTIN_O </summary>

|Predecessors | Count | Percentage | 
|---|---:|---:|
| BINARY_SUBSCR | 403,920 | 71.6% |
| LOAD_FAST | 80,080 | 14.2% |
| BINARY_OP | 79,960 | 14.2% |
| CALL | 140 | 0.0% |

|Successors | Count | Percentage | 
|---|---:|---:|
| STORE_FAST | 564,100 | 100.0% |


</details>

### LOAD_ATTR_NONDESCRIPTOR_WITH_VALUES

<details>
<summary> Successors and predecessors for LOAD_ATTR_NONDESCRIPTOR_WITH_VALUES </summary>

|Predecessors | Count | Percentage | 
|---|---:|---:|
| LOAD_FAST | 16,967,920 | 66.6% |
| LOAD_FAST_LOAD_FAST | 8,493,640 | 33.4% |
| LOAD_ATTR | 660 | 0.0% |

|Successors | Count | Percentage | 
|---|---:|---:|
| LOAD_GLOBAL_BUILTIN | 16,963,720 | 66.6% |
| BINARY_OP | 8,490,220 | 33.3% |
| LOAD_CONST | 4,020 | 0.0% |
| LOAD_FAST | 4,020 | 0.0% |
| CALL | 180 | 0.0% |


</details>

### TO_BOOL_BOOL

<details>
<summary> Successors and predecessors for TO_BOOL_BOOL </summary>

|Predecessors | Count | Percentage | 
|---|---:|---:|
| CALL_ISINSTANCE | 80,450,240 | 82.6% |
| LOAD_ATTR_INSTANCE_VALUE | 16,963,720 | 17.4% |
| TO_BOOL | 100 | 0.0% |

|Successors | Count | Percentage | 
|---|---:|---:|
| POP_JUMP_IF_FALSE | 97,414,060 | 100.0% |


</details>

### COMPARE_OP_FLOAT

<details>
<summary> Successors and predecessors for COMPARE_OP_FLOAT </summary>

|Predecessors | Count | Percentage | 
|---|---:|---:|
| LOAD_CONST | 7,999,960 | 95.3% |
| LOAD_FAST_LOAD_FAST | 395,960 | 4.7% |
| COMPARE_OP | 40 | 0.0% |

|Successors | Count | Percentage | 
|---|---:|---:|
| POP_JUMP_IF_TRUE | 8,395,960 | 100.0% |


</details>

### END_FOR

<details>
<summary> Successors and predecessors for END_FOR </summary>

|Predecessors | Count | Percentage | 
|---|---:|---:|
| RETURN_CONST | 80 | 100.0% |

|Successors | Count | Percentage | 
|---|---:|---:|
| LOAD_FAST | 80 | 100.0% |


</details>

### RETURN_GENERATOR

<details>
<summary> Successors and predecessors for RETURN_GENERATOR </summary>

|Predecessors | Count | Percentage | 
|---|---:|---:|
| CALL_PY_EXACT_ARGS | 60 | 75.0% |
| CALL | 20 | 25.0% |

|Successors | Count | Percentage | 
|---|---:|---:|
| GET_ITER | 80 | 100.0% |


</details>

### YIELD_VALUE

<details>
<summary> Successors and predecessors for YIELD_VALUE </summary>

|Predecessors | Count | Percentage | 
|---|---:|---:|
| BUILD_TUPLE | 800,000 | 100.0% |

|Successors | Count | Percentage | 
|---|---:|---:|
| UNPACK_SEQUENCE_TWO_TUPLE | 799,960 | 100.0% |
| INTERPRETER_EXIT | 20 | 0.0% |
| UNPACK_SEQUENCE | 20 | 0.0% |


</details>

### BINARY_SUBSCR_LIST_INT

<details>
<summary> Successors and predecessors for BINARY_SUBSCR_LIST_INT </summary>

|Predecessors | Count | Percentage | 
|---|---:|---:|
| LOAD_FAST | 79,635,080 | 99.0% |
| BINARY_SUBSCR_TUPLE_INT | 799,960 | 1.0% |
| BINARY_SUBSCR | 40 | 0.0% |

|Successors | Count | Percentage | 
|---|---:|---:|
| RETURN_VALUE | 79,635,100 | 99.0% |
| LOAD_FAST | 799,980 | 1.0% |


</details>

### BINARY_SUBSCR_TUPLE_INT

<details>
<summary> Successors and predecessors for BINARY_SUBSCR_TUPLE_INT </summary>

|Predecessors | Count | Percentage | 
|---|---:|---:|
| LOAD_CONST | 1,599,920 | 100.0% |
| BINARY_SUBSCR | 40 | 0.0% |

|Successors | Count | Percentage | 
|---|---:|---:|
| STORE_SUBSCR | 799,980 | 50.0% |
| BINARY_SUBSCR_LIST_INT | 799,960 | 50.0% |
| BINARY_SUBSCR | 20 | 0.0% |


</details>

### CALL_ISINSTANCE

<details>
<summary> Successors and predecessors for CALL_ISINSTANCE </summary>

|Predecessors | Count | Percentage | 
|---|---:|---:|
| LOAD_GLOBAL_BUILTIN | 80,450,240 | 100.0% |
| CALL | 40 | 0.0% |

|Successors | Count | Percentage | 
|---|---:|---:|
| TO_BOOL_BOOL | 80,450,240 | 100.0% |
| TO_BOOL | 40 | 0.0% |


</details>

### FOR_ITER_GEN

<details>
<summary> Successors and predecessors for FOR_ITER_GEN </summary>

|Predecessors | Count | Percentage | 
|---|---:|---:|
| JUMP_BACKWARD | 799,980 | 100.0% |
| GET_ITER | 60 | 0.0% |
| FOR_ITER | 20 | 0.0% |

|Successors | Count | Percentage | 
|---|---:|---:|
| RESUME_CHECK | 799,980 | 100.0% |
| POP_TOP | 60 | 0.0% |
| RESUME | 20 | 0.0% |


</details>

### STORE_SUBSCR_LIST_INT

<details>
<summary> Successors and predecessors for STORE_SUBSCR_LIST_INT </summary>

|Predecessors | Count | Percentage | 
|---|---:|---:|
| LOAD_FAST | 15,160 | 99.9% |
| STORE_SUBSCR | 20 | 0.1% |

|Successors | Count | Percentage | 
|---|---:|---:|
| RETURN_CONST | 15,180 | 100.0% |


</details>


</details>

## Specialization stats

<details>
<summary> specialization stats by family </summary>

### BINARY_OP

<details>
<summary> specialization stats for BINARY_OP family </summary>

|Kind | Count | Ratio | 
|---|---:|---:|
|     deferred | 41,550,700 | 3.1% |
|          hit | 1,298,235,140 | 96.9% |

| | Count | Ratio | 
|---|---:|---:|
| Success | 2,460 | 13.3% |
| Failure | 16,020 | 86.7% |

|Failure kind | Count | Ratio | 
|---|---:|---:|
| lshift | 4,500 | 28.1% |
| rshift | 4,340 | 27.1% |
| add different types | 2,920 | 18.2% |
| multiply different types | 1,460 | 9.1% |
| true divide other | 840 | 5.2% |
| remainder | 780 | 4.9% |
| true divide float | 540 | 3.4% |
| floor divide | 500 | 3.1% |
| true divide different types | 140 | 0.9% |


</details>

### BINARY_SLICE

<details>
<summary> specialization stats for BINARY_SLICE family </summary>


</details>

### BINARY_SUBSCR

<details>
<summary> specialization stats for BINARY_SUBSCR family </summary>

|Kind | Count | Ratio | 
|---|---:|---:|
|     deferred | 616,427,980 | 75.5% |
|          hit | 200,085,860 | 24.5% |

| | Count | Ratio | 
|---|---:|---:|
| Success | 380 | 0.2% |
| Failure | 157,580 | 99.8% |

|Failure kind | Count | Ratio | 
|---|---:|---:|
| array int | 157,580 | 100.0% |


</details>

### CALL

<details>
<summary> specialization stats for CALL family </summary>

|Kind | Count | Ratio | 
|---|---:|---:|
|     deferred | 20,280 | 0.0% |
|          hit | 171,303,000 | 100.0% |

| | Count | Ratio | 
|---|---:|---:|
| Success | 1,480 | 63.2% |
| Failure | 860 | 36.8% |

|Failure kind | Count | Ratio | 
|---|---:|---:|
| class no vectorcall | 420 | 48.8% |
| cfunc noargs | 300 | 34.9% |
| cfunc varargs keywords | 80 | 9.3% |
| wrong number arguments | 60 | 7.0% |


</details>

### COMPARE_OP

<details>
<summary> specialization stats for COMPARE_OP family </summary>

|Kind | Count | Ratio | 
|---|---:|---:|
|     deferred | 16,972,420 | 6.3% |
|          hit | 251,496,140 | 93.7% |

| | Count | Ratio | 
|---|---:|---:|
| Success | 580 | 10.7% |
| Failure | 4,860 | 89.3% |

|Failure kind | Count | Ratio | 
|---|---:|---:|
| float long | 4,860 | 100.0% |


</details>

### FOR_ITER

<details>
<summary> specialization stats for FOR_ITER family </summary>

|Kind | Count | Ratio | 
|---|---:|---:|
|     deferred | 8,720 | 0.0% |
|          hit | 189,969,040 | 100.0% |

| | Count | Ratio | 
|---|---:|---:|
| Success | 640 | 82.1% |
| Failure | 140 | 17.9% |

|Failure kind | Count | Ratio | 
|---|---:|---:|
| zip | 140 | 100.0% |


</details>

### LOAD_ATTR

<details>
<summary> specialization stats for LOAD_ATTR family </summary>

|Kind | Count | Ratio | 
|---|---:|---:|
|     deferred | 1,960 | 0.0% |
|          hit | 438,511,480 | 100.0% |
|         miss | 12,240 | 0.0% |

| | Count | Ratio | 
|---|---:|---:|
| Success | 1,960 | 100.0% |
| Failure | 0 | 0.0% |


</details>

### LOAD_GLOBAL

<details>
<summary> specialization stats for LOAD_GLOBAL family </summary>

|Kind | Count | Ratio | 
|---|---:|---:|
|     deferred | 1,980 | 0.0% |
|          hit | 188,787,940 | 100.0% |

| | Count | Ratio | 
|---|---:|---:|
| Success | 1,980 | 100.0% |
| Failure | 0 | 0.0% |


</details>

### POP_JUMP_IF_FALSE

<details>
<summary> specialization stats for POP_JUMP_IF_FALSE family </summary>


</details>

### POP_JUMP_IF_NONE

<details>
<summary> specialization stats for POP_JUMP_IF_NONE family </summary>


</details>

### POP_JUMP_IF_TRUE

<details>
<summary> specialization stats for POP_JUMP_IF_TRUE family </summary>


</details>

### STORE_ATTR

<details>
<summary> specialization stats for STORE_ATTR family </summary>

|Kind | Count | Ratio | 
|---|---:|---:|
|     deferred | 720 | 0.0% |
|          hit | 33,929,600 | 100.0% |

| | Count | Ratio | 
|---|---:|---:|
| Success | 720 | 100.0% |
| Failure | 0 | 0.0% |


</details>

### STORE_SLICE

<details>
<summary> specialization stats for STORE_SLICE family </summary>


</details>

### STORE_SUBSCR

<details>
<summary> specialization stats for STORE_SUBSCR family </summary>

|Kind | Count | Ratio | 
|---|---:|---:|
|     deferred | 253,885,620 | 100.0% |
|          hit | 15,180 | 0.0% |

| | Count | Ratio | 
|---|---:|---:|
| Success | 20 | 0.0% |
| Failure | 67,440 | 100.0% |

|Failure kind | Count | Ratio | 
|---|---:|---:|
| array int | 64,720 | 96.0% |
| py simple | 2,720 | 4.0% |


</details>

### TO_BOOL

<details>
<summary> specialization stats for TO_BOOL family </summary>

|Kind | Count | Ratio | 
|---|---:|---:|
|     deferred | 100 | 0.0% |
|          hit | 97,414,060 | 100.0% |

| | Count | Ratio | 
|---|---:|---:|
| Success | 100 | 100.0% |
| Failure | 0 | 0.0% |


</details>

### UNPACK_SEQUENCE

<details>
<summary> specialization stats for UNPACK_SEQUENCE family </summary>

|Kind | Count | Ratio | 
|---|---:|---:|
|     deferred | 80 | 0.0% |
|          hit | 46,907,120 | 100.0% |

| | Count | Ratio | 
|---|---:|---:|
| Success | 80 | 100.0% |
| Failure | 0 | 0.0% |


</details>


</details>

## Specialization effectiveness

<details>
<summary> specialization effectiveness </summary>

|Instructions | Count | Ratio | 
|---|---:|---:|
| Basic | 5,132,518,540 | 53.8% |
| Not specialized | 1,295,018,980 | 13.6% |
| Specialized hits | 3,107,100,600 | 32.6% |
| Specialized misses | 12,240 | 0.0% |

### Deferred by instruction

<details>
<summary> deferred by instruction </summary>

|Name | Count | Ratio | 
|---|---:|---:|
| BINARY_SUBSCR | 616,427,980 | 66.4% |
| STORE_SUBSCR | 253,885,620 | 27.3% |
| BINARY_OP | 41,550,700 | 4.5% |
| COMPARE_OP | 16,972,420 | 1.8% |
| CALL | 20,280 | 0.0% |
| FOR_ITER | 8,720 | 0.0% |
| LOAD_GLOBAL | 1,980 | 0.0% |
| LOAD_ATTR | 1,960 | 0.0% |
| STORE_ATTR | 720 | 0.0% |
| TO_BOOL | 100 | 0.0% |


</details>

### Misses by instruction

<details>
<summary> misses by instruction </summary>

|Name | Count | Ratio | 
|---|---:|---:|
| LOAD_ATTR_NONDESCRIPTOR_WITH_VALUES | 12,240 | 100.0% |
| CACHE | 0 | 0.0% |
| GET_ITER | 0 | 0.0% |
| INTERPRETER_EXIT | 0 | 0.0% |
| NOP | 0 | 0.0% |
| POP_TOP | 0 | 0.0% |
| PUSH_NULL | 0 | 0.0% |
| RETURN_VALUE | 0 | 0.0% |
| BUILD_LIST | 0 | 0.0% |
| BUILD_TUPLE | 0 | 0.0% |


</details>


</details>

## Call stats

<details>
<summary> Inlined calls and frame stats </summary>

| | Count | Ratio | 
|---|---:|---:|
| Calls to PyEval_EvalDefault | 8,499,020 | 4.5% |
| Calls to Python functions inlined | 181,947,940 | 95.5% |
| Calls via PyEval_EvalFrame (total) | 8,499,020 | 4.5% |
| Calls via PyEval_EvalFrame (vector) | 8,499,000 | 4.5% |
| Calls via PyEval_EvalFrame (generator) | 20 | 0.0% |
| Calls via PyEval_EvalFrame (legacy) | 0 | 0.0% |
| Calls via PyEval_EvalFrame (function vectorcall) | 8,499,000 | 4.5% |
| Calls via PyEval_EvalFrame (build class) | 0 | 0.0% |
| Calls via PyEval_EvalFrame (slot) | 8,498,700 | 4.5% |
| Calls via PyEval_EvalFrame (function ex) | 800 | 0.0% |
| Calls via PyEval_EvalFrame (api) | 0 | 0.0% |
| Calls via PyEval_EvalFrame (method) | 0 | 0.0% |
| Frame objects created | 0 | 0.0% |
| Frames pushed | 181,146,760 | 95.1% |


</details>

## Object stats

<details>
<summary> allocations, frees and dict materializatons </summary>

| | Count | Ratio | 
|---|---:|---:|
| Allocations from freelist | 818,723,360 | 57.5% |
| Frees to freelist | 818,725,940 |  |
| Allocations | 606,285,880 | 42.5% |
| Allocations to 512 bytes | 606,269,240 | 42.5% |
| Allocations to 4 kbytes | 16,080 | 0.0% |
| Allocations over 4 kbytes | 560 | 0.0% |
| Frees | 606,286,620 |  |
| New values | 300 |  |
| Interpreter increfs | 3,541,849,200 | 83.1% |
| Interpreter decrefs | 4,983,559,500 | 87.6% |
| Increfs | 722,599,122 | 16.9% |
| Decrefs | 705,860,425 | 12.4% |
| Materialize dict (on request) | 0 | 0.0% |
| Materialize dict (new key) | 0 | 0.0% |
| Materialize dict (too big) | 0 | 0.0% |
| Materialize dict (str subclass) | 0 | 0.0% |
| Dematerialize dict | 0 | 0.0% |
| Method cache hits | 16,114 |  |
| Method cache misses | 1,126 |  |
| Method cache collisions | 863 |  |
| Method cache dunder hits | 88,309,758 |  |
| Method cache dunder misses | 282 |  |


</details>

## GC stats

<details>
<summary> GC collections and effectiveness </summary>

|Generation | Collections | Objects collected | Object visits | 
|---:|---:|---:|---:|
| 0 | 20 | 1,980 | 134,400 |
| 1 | 0 | 0 | 0 |
| 2 | 0 | 0 | 0 |


</details>

## Optimization (Tier 2) stats

<details>
<summary> statistics about the Tier 2 optimizer </summary>

| | Count | Ratio | 
|---|---:|---:|
| Optimization attempts | 0 |  |
| Traces created | 0 |  |
| Trace stack overflow | 0 |  |
| Trace stack underflow | 0 |  |
| Trace too long | 0 |  |
| Trace too short | 0 |  |
| Inner loop found | 0 |  |
| Recursive call | 0 |  |
| Traces executed | 0 |  |
| Uops executed | 0 |  |

### Trace length histogram

<details>
<summary> trace length histogram </summary>

|Range | Count | Ratio | 
|---|---:|---:|
| <= 1 | 0 |  |


</details>

### Optimized trace length histogram

<details>
<summary> optimized trace length histogram </summary>

|Range | Count | Ratio | 
|---|---:|---:|
| <= 1 | 0 |  |


</details>

### Trace run length histogram

<details>
<summary> trace run length histogram </summary>

|Range | Count | Ratio | 
|---|---:|---:|
| <= 1 | 0 |  |


</details>

### Uop execution stats

<details>
<summary> uop execution stats </summary>


</details>

### Unsupported opcodes

<details>
<summary> unsupported opcodes </summary>


</details>


</details>

## Meta stats

<details>
<summary> Meta statistics </summary>

| | Count | 
|---|---:|
| Number of data files | 100 |


</details>

---
Stats gathered on: 2024-09-10
