
# Pystats results

- benchmark: deltablue
- fork: python
- ref: v3.13.0a4
- commit hash: 9d34f60
- commit date: 2024-02-15T14:38:42+01:00

## Execution counts

<details>
<summary> execution counts for all instructions </summary>

|Name | Count | Self | Cumulative | Miss ratio | 
|---|---:|---:|---:|---:|
| LOAD_FAST | 391,496,320 | 20.2% | 20.2% |  |
| LOAD_ATTR_INSTANCE_VALUE | 268,408,620 | 13.9% | 34.1% | 1.5% |
| RESUME_CHECK | 131,636,640 | 6.8% | 40.9% | 0.0% |
| CALL_PY_EXACT_ARGS | 123,166,680 | 6.4% | 47.3% | 2.8% |
| LOAD_ATTR_METHOD_WITH_VALUES | 121,385,540 | 6.3% | 53.6% | 5.5% |
| LOAD_GLOBAL_MODULE | 94,470,280 | 4.9% | 58.4% |  |
| POP_JUMP_IF_FALSE | 93,130,320 | 4.8% | 63.3% |  |
| COMPARE_OP_INT | 87,805,100 | 4.5% | 67.8% |  |
| RETURN_VALUE | 81,860,940 | 4.2% | 72.0% |  |
| LOAD_ATTR_CLASS | 78,745,360 | 4.1% | 76.1% |  |
| STORE_FAST | 60,257,680 | 3.1% | 79.2% |  |
| STORE_ATTR_INSTANCE_VALUE | 55,089,540 | 2.8% | 82.1% | 3.4% |
| POP_TOP | 53,102,380 | 2.7% | 84.8% |  |
| RETURN_CONST | 51,095,040 | 2.6% | 87.4% |  |
| FOR_ITER_LIST | 41,702,280 | 2.2% | 89.6% |  |
| JUMP_BACKWARD | 41,364,480 | 2.1% | 91.7% |  |
| LOAD_FAST_LOAD_FAST | 20,323,840 | 1.1% | 92.8% |  |
| TO_BOOL_BOOL | 18,201,080 | 0.9% | 93.7% |  |
| LOAD_ATTR | 17,765,040 | 0.9% | 94.6% |  |
| POP_JUMP_IF_TRUE | 12,500,480 | 0.6% | 95.3% |  |
| LOAD_CONST | 9,244,240 | 0.5% | 95.8% |  |
| LOAD_GLOBAL_BUILTIN | 7,871,600 | 0.4% | 96.2% |  |
| BINARY_OP_ADD_INT | 7,165,340 | 0.4% | 96.5% |  |
| CALL_BOUND_METHOD_EXACT_ARGS | 6,955,340 | 0.4% | 96.9% |  |
| BINARY_OP_MULTIPLY_INT | 6,366,660 | 0.3% | 97.2% |  |
| CALL_LIST_APPEND | 5,997,860 | 0.3% | 97.5% |  |
| COMPARE_OP | 5,512,420 | 0.3% | 97.8% |  |
| COPY | 4,656,640 | 0.2% | 98.1% |  |
| CALL_LEN | 4,446,600 | 0.2% | 98.3% |  |
| TO_BOOL_INT | 4,446,600 | 0.2% | 98.5% |  |
| GET_ITER | 4,057,680 | 0.2% | 98.7% |  |
| CALL | 3,981,820 | 0.2% | 98.9% |  |
| COPY_FREE_VARS | 3,402,320 | 0.2% | 99.1% |  |
| LOAD_SUPER_ATTR_METHOD | 3,402,020 | 0.2% | 99.3% |  |
| CALL_METHOD_DESCRIPTOR_FAST | 3,185,780 | 0.2% | 99.5% | 100.0% |
| POP_JUMP_IF_NONE | 2,869,760 | 0.1% | 99.6% |  |
| FOR_ITER_RANGE | 1,405,380 | 0.1% | 99.7% |  |
| EXIT_INIT_CHECK | 1,318,140 | 0.1% | 99.8% |  |
| CALL_ALLOC_AND_ENTER_INIT | 1,318,140 | 0.1% | 99.8% |  |
| BINARY_OP | 856,520 | 0.0% | 99.9% |  |
| SWAP | 796,160 | 0.0% | 99.9% |  |
| JUMP_FORWARD | 514,560 | 0.0% | 99.9% |  |
| BINARY_SUBSCR | 507,440 | 0.0% | 100.0% |  |
| UNARY_NOT | 271,360 | 0.0% | 100.0% |  |
| INTERPRETER_EXIT | 261,380 | 0.0% | 100.0% |  |
| BINARY_OP_SUBTRACT_INT | 89,540 | 0.0% | 100.0% |  |
| LOAD_ATTR_SLOT | 61,320 | 0.0% | 100.0% |  |
| CALL_BUILTIN_CLASS | 22,980 | 0.0% | 100.0% |  |
| CALL_METHOD_DESCRIPTOR_O | 10,400 | 0.0% | 100.0% | 100.0% |
| BUILD_CONST_KEY_MAP | 10,240 | 0.0% | 100.0% |  |
| BINARY_SUBSCR_DICT | 10,220 | 0.0% | 100.0% |  |
| STORE_GLOBAL | 5,120 | 0.0% | 100.0% |  |
| LOAD_GLOBAL | 4,080 | 0.0% | 100.0% |  |
| PUSH_NULL | 2,880 | 0.0% | 100.0% |  |
| LOAD_FAST_CHECK | 2,560 | 0.0% | 100.0% |  |
| STORE_FAST_STORE_FAST | 2,560 | 0.0% | 100.0% |  |
| UNPACK_SEQUENCE_TUPLE | 2,540 | 0.0% | 100.0% |  |
| STORE_ATTR | 2,200 | 0.0% | 100.0% |  |
| TO_BOOL | 1,280 | 0.0% | 100.0% |  |
| RESUME | 1,200 | 0.0% | 100.0% | 296.7% |
| FOR_ITER | 520 | 0.0% | 100.0% |  |
| LOAD_SUPER_ATTR | 440 | 0.0% | 100.0% |  |
| LOAD_DEREF | 160 | 0.0% | 100.0% |  |
| LOAD_ATTR_MODULE | 120 | 0.0% | 100.0% |  |
| NOP | 80 | 0.0% | 100.0% |  |
| CALL_FUNCTION_EX | 80 | 0.0% | 100.0% |  |
| BINARY_OP_SUBTRACT_FLOAT | 60 | 0.0% | 100.0% |  |
| UNPACK_SEQUENCE | 40 | 0.0% | 100.0% |  |


</details>

## Pair counts

<details>
<summary> Pair counts for top 100 pairs </summary>

|Pair | Count | Self | Cumulative | 
|---|---:|---:|---:|
| LOAD_FAST LOAD_ATTR_INSTANCE_VALUE | 210,659,280 | 10.9% | 10.9% |
| RESUME_CHECK LOAD_FAST | 124,154,240 | 6.4% | 17.3% |
| CALL_PY_EXACT_ARGS RESUME_CHECK | 121,275,820 | 6.3% | 23.6% |
| LOAD_FAST LOAD_ATTR_METHOD_WITH_VALUES | 115,525,680 | 6.0% | 29.5% |
| LOAD_ATTR_METHOD_WITH_VALUES CALL_PY_EXACT_ARGS | 109,241,200 | 5.6% | 35.2% |
| POP_JUMP_IF_FALSE LOAD_FAST | 81,198,080 | 4.2% | 39.4% |
| LOAD_GLOBAL_MODULE LOAD_ATTR_CLASS | 78,745,120 | 4.1% | 43.5% |
| COMPARE_OP_INT POP_JUMP_IF_FALSE | 76,991,800 | 4.0% | 47.4% |
| LOAD_ATTR_INSTANCE_VALUE LOAD_GLOBAL_MODULE | 75,414,840 | 3.9% | 51.3% |
| LOAD_ATTR_CLASS COMPARE_OP_INT | 75,409,760 | 3.9% | 55.2% |
| LOAD_ATTR_INSTANCE_VALUE RETURN_VALUE | 67,089,780 | 3.5% | 58.7% |
| LOAD_ATTR_INSTANCE_VALUE LOAD_FAST | 50,917,820 | 2.6% | 61.3% |
| STORE_FAST LOAD_FAST | 50,457,920 | 2.6% | 63.9% |
| RETURN_CONST POP_TOP | 47,915,520 | 2.5% | 66.4% |
| JUMP_BACKWARD FOR_ITER_LIST | 37,667,720 | 1.9% | 68.4% |
| FOR_ITER_LIST STORE_FAST | 37,667,720 | 1.9% | 70.3% |
| STORE_ATTR_INSTANCE_VALUE RETURN_CONST | 37,554,820 | 1.9% | 72.3% |
| POP_TOP JUMP_BACKWARD | 31,490,640 | 1.6% | 73.9% |
| RETURN_VALUE LOAD_ATTR_INSTANCE_VALUE | 28,710,280 | 1.5% | 75.4% |
| RETURN_VALUE STORE_ATTR_INSTANCE_VALUE | 27,924,360 | 1.4% | 76.8% |
| LOAD_ATTR_INSTANCE_VALUE LOAD_ATTR_INSTANCE_VALUE | 27,204,200 | 1.4% | 78.2% |
| LOAD_FAST STORE_ATTR_INSTANCE_VALUE | 12,233,020 | 0.6% | 78.9% |
| LOAD_FAST CALL_PY_EXACT_ARGS | 12,023,280 | 0.6% | 79.5% |
| LOAD_ATTR LOAD_FAST | 11,743,860 | 0.6% | 80.1% |
| TO_BOOL_BOOL POP_JUMP_IF_FALSE | 11,663,020 | 0.6% | 80.7% |
| LOAD_ATTR_METHOD_WITH_VALUES LOAD_FAST | 10,720,880 | 0.6% | 81.2% |
| RETURN_VALUE TO_BOOL_BOOL | 10,395,620 | 0.5% | 81.8% |
| POP_TOP LOAD_FAST | 9,326,080 | 0.5% | 82.3% |
| COMPARE_OP_INT RETURN_VALUE | 9,277,380 | 0.5% | 82.7% |
| RETURN_VALUE STORE_FAST | 8,867,700 | 0.5% | 83.2% |
| STORE_ATTR_INSTANCE_VALUE LOAD_FAST | 8,680,640 | 0.4% | 83.6% |
| LOAD_FAST LOAD_ATTR | 8,594,160 | 0.4% | 84.1% |
| LOAD_FAST_LOAD_FAST STORE_ATTR_INSTANCE_VALUE | 7,095,780 | 0.4% | 84.5% |
| LOAD_ATTR_INSTANCE_VALUE STORE_FAST | 7,022,000 | 0.4% | 84.8% |
| LOAD_ATTR_INSTANCE_VALUE STORE_ATTR_INSTANCE_VALUE | 7,003,920 | 0.4% | 85.2% |
| CALL_BOUND_METHOD_EXACT_ARGS RESUME_CHECK | 6,955,340 | 0.4% | 85.5% |
| LOAD_GLOBAL_MODULE LOAD_ATTR | 6,492,160 | 0.3% | 85.9% |
| LOAD_FAST COMPARE_OP_INT | 6,471,320 | 0.3% | 86.2% |
| STORE_FAST LOAD_FAST_LOAD_FAST | 6,348,800 | 0.3% | 86.5% |
| TO_BOOL_BOOL POP_JUMP_IF_TRUE | 6,266,720 | 0.3% | 86.9% |
| BINARY_OP_ADD_INT LOAD_FAST | 5,859,820 | 0.3% | 87.2% |
| BINARY_OP_MULTIPLY_INT LOAD_FAST | 5,859,820 | 0.3% | 87.5% |
| LOAD_ATTR_INSTANCE_VALUE BINARY_OP_ADD_INT | 5,859,800 | 0.3% | 87.8% |
| LOAD_ATTR_INSTANCE_VALUE BINARY_OP_MULTIPLY_INT | 5,859,800 | 0.3% | 88.1% |
| POP_JUMP_IF_TRUE LOAD_FAST | 5,488,640 | 0.3% | 88.4% |
| LOAD_FAST CALL_LIST_APPEND | 5,480,560 | 0.3% | 88.6% |
| COMPARE_OP POP_JUMP_IF_TRUE | 5,470,780 | 0.3% | 88.9% |
| LOAD_FAST_LOAD_FAST COMPARE_OP | 5,470,760 | 0.3% | 89.2% |
| LOAD_ATTR_INSTANCE_VALUE COMPARE_OP_INT | 4,897,200 | 0.3% | 89.5% |
| LOAD_ATTR_INSTANCE_VALUE CALL_BOUND_METHOD_EXACT_ARGS | 4,896,960 | 0.3% | 89.7% |
| RETURN_VALUE LOAD_FAST | 4,656,640 | 0.2% | 90.0% |
| LOAD_GLOBAL_BUILTIN LOAD_FAST | 4,456,820 | 0.2% | 90.2% |
| TO_BOOL_INT POP_JUMP_IF_FALSE | 4,446,600 | 0.2% | 90.4% |
| LOAD_FAST CALL_LEN | 4,446,480 | 0.2% | 90.6% |
| CALL_LEN TO_BOOL_INT | 4,446,480 | 0.2% | 90.9% |
| POP_JUMP_IF_TRUE JUMP_BACKWARD | 4,428,800 | 0.2% | 91.1% |
| POP_JUMP_IF_FALSE LOAD_GLOBAL_MODULE | 4,136,440 | 0.2% | 91.3% |
| GET_ITER FOR_ITER_LIST | 4,034,440 | 0.2% | 91.5% |
| LOAD_CONST LOAD_FAST | 3,978,240 | 0.2% | 91.7% |
| LOAD_GLOBAL_MODULE LOAD_FAST | 3,947,080 | 0.2% | 91.9% |
| POP_TOP RETURN_CONST | 3,916,840 | 0.2% | 92.1% |
| POP_TOP LOAD_FAST_LOAD_FAST | 3,906,560 | 0.2% | 92.3% |
| COPY TO_BOOL_BOOL | 3,860,320 | 0.2% | 92.5% |
| COPY_FREE_VARS RESUME_CHECK | 3,402,080 | 0.2% | 92.7% |
| LOAD_FAST LOAD_SUPER_ATTR_METHOD | 3,401,800 | 0.2% | 92.9% |
| LOAD_GLOBAL_BUILTIN LOAD_GLOBAL_MODULE | 3,401,800 | 0.2% | 93.1% |
| STORE_ATTR_INSTANCE_VALUE LOAD_GLOBAL_MODULE | 3,381,520 | 0.2% | 93.2% |
| LOAD_FAST RETURN_VALUE | 3,379,280 | 0.2% | 93.4% |
| LOAD_ATTR_CLASS LOAD_FAST | 3,335,520 | 0.2% | 93.6% |
| RESUME_CHECK LOAD_GLOBAL_BUILTIN | 3,145,840 | 0.2% | 93.8% |
| LOAD_ATTR LOAD_CONST | 3,136,060 | 0.2% | 93.9% |
| CALL_METHOD_DESCRIPTOR_FAST STORE_FAST | 3,125,700 | 0.2% | 94.1% |
| LOAD_CONST CALL_METHOD_DESCRIPTOR_FAST | 3,125,640 | 0.2% | 94.2% |
| LOAD_ATTR_INSTANCE_VALUE COPY | 3,087,300 | 0.2% | 94.4% |
| FOR_ITER_LIST RETURN_CONST | 2,956,800 | 0.2% | 94.5% |
| STORE_FAST LOAD_GLOBAL_MODULE | 2,879,520 | 0.1% | 94.7% |
| LOAD_FAST POP_JUMP_IF_NONE | 2,859,520 | 0.1% | 94.8% |
| POP_JUMP_IF_FALSE JUMP_BACKWARD | 2,839,040 | 0.1% | 95.0% |
| LOAD_FAST GET_ITER | 2,621,520 | 0.1% | 95.1% |
| STORE_ATTR_INSTANCE_VALUE LOAD_CONST | 2,608,480 | 0.1% | 95.3% |
| LOAD_ATTR_INSTANCE_VALUE LOAD_ATTR | 2,604,000 | 0.1% | 95.4% |
| POP_TOP LOAD_GLOBAL_BUILTIN | 2,603,360 | 0.1% | 95.5% |
| CALL_LIST_APPEND RETURN_CONST | 2,593,240 | 0.1% | 95.7% |
| LOAD_ATTR_INSTANCE_VALUE TO_BOOL_BOOL | 2,329,480 | 0.1% | 95.8% |
| JUMP_BACKWARD LOAD_FAST | 2,314,240 | 0.1% | 95.9% |
| POP_JUMP_IF_FALSE POP_TOP | 2,314,240 | 0.1% | 96.0% |
| LOAD_GLOBAL_MODULE CALL | 2,134,920 | 0.1% | 96.1% |
| LOAD_GLOBAL_MODULE LOAD_ATTR_METHOD_WITH_VALUES | 2,104,120 | 0.1% | 96.2% |
| POP_JUMP_IF_FALSE RETURN_CONST | 2,099,200 | 0.1% | 96.4% |
| RESUME_CHECK LOAD_GLOBAL_MODULE | 2,098,920 | 0.1% | 96.5% |
| LOAD_ATTR LOAD_FAST_LOAD_FAST | 2,058,260 | 0.1% | 96.6% |
| LOAD_FAST_LOAD_FAST CALL_BOUND_METHOD_EXACT_ARGS | 2,058,200 | 0.1% | 96.7% |
| STORE_ATTR_INSTANCE_VALUE LOAD_FAST_LOAD_FAST | 2,058,140 | 0.1% | 96.8% |
| CALL_LIST_APPEND JUMP_BACKWARD | 1,827,760 | 0.1% | 96.9% |
| CALL_PY_EXACT_ARGS COPY_FREE_VARS | 1,825,180 | 0.1% | 97.0% |
| LOAD_ATTR_INSTANCE_VALUE LOAD_ATTR_METHOD_WITH_VALUES | 1,817,360 | 0.1% | 97.1% |
| LOAD_FAST_LOAD_FAST LOAD_ATTR_METHOD_WITH_VALUES | 1,812,400 | 0.1% | 97.2% |
| CALL STORE_FAST | 1,605,420 | 0.1% | 97.2% |
| RETURN_CONST TO_BOOL_BOOL | 1,594,740 | 0.1% | 97.3% |
| CALL POP_TOP | 1,579,920 | 0.1% | 97.4% |


</details>

## Predecessor/Successor Pairs

<details>
<summary> Top 5 predecessors and successors of each opcode </summary>

### CACHE

<details>
<summary> Successors and predecessors for CACHE </summary>

|Successors | Count | Percentage | 
|---|---:|---:|
| COPY_FREE_VARS | 258,820 | 99.0% |
| RESUME_CHECK | 2,540 | 1.0% |
| RESUME | 20 | 0.0% |


</details>

### BINARY_SUBSCR

<details>
<summary> Successors and predecessors for BINARY_SUBSCR </summary>

|Predecessors | Count | Percentage | 
|---|---:|---:|
| LOAD_FAST_LOAD_FAST | 506,880 | 99.9% |
| BINARY_SUBSCR | 520 | 0.1% |
| LOAD_ATTR | 20 | 0.0% |
| LOAD_ATTR_INSTANCE_VALUE | 20 | 0.0% |

|Successors | Count | Percentage | 
|---|---:|---:|
| LOAD_ATTR_INSTANCE_VALUE | 506,800 | 99.9% |
| BINARY_SUBSCR | 520 | 0.1% |
| LOAD_ATTR | 80 | 0.0% |
| RETURN_VALUE | 20 | 0.0% |
| BINARY_SUBSCR_DICT | 20 | 0.0% |


</details>

### EXIT_INIT_CHECK

<details>
<summary> Successors and predecessors for EXIT_INIT_CHECK </summary>

|Predecessors | Count | Percentage | 
|---|---:|---:|
| RETURN_CONST | 1,318,140 | 100.0% |

|Successors | Count | Percentage | 
|---|---:|---:|
| RETURN_VALUE | 1,318,140 | 100.0% |


</details>

### GET_ITER

<details>
<summary> Successors and predecessors for GET_ITER </summary>

|Predecessors | Count | Percentage | 
|---|---:|---:|
| LOAD_FAST | 2,621,520 | 64.6% |
| LOAD_ATTR_INSTANCE_VALUE | 1,413,060 | 34.8% |
| CALL_BUILTIN_CLASS | 22,920 | 0.6% |
| CALL | 120 | 0.0% |
| LOAD_ATTR | 60 | 0.0% |

|Successors | Count | Percentage | 
|---|---:|---:|
| FOR_ITER_LIST | 4,034,440 | 99.4% |
| FOR_ITER_RANGE | 22,980 | 0.6% |
| FOR_ITER | 260 | 0.0% |


</details>

### INTERPRETER_EXIT

<details>
<summary> Successors and predecessors for INTERPRETER_EXIT </summary>

|Predecessors | Count | Percentage | 
|---|---:|---:|
| RETURN_CONST | 261,380 | 100.0% |


</details>

### NOP

<details>
<summary> Successors and predecessors for NOP </summary>

|Predecessors | Count | Percentage | 
|---|---:|---:|
| POP_TOP | 80 | 100.0% |

|Successors | Count | Percentage | 
|---|---:|---:|
| LOAD_DEREF | 80 | 100.0% |


</details>

### POP_TOP

<details>
<summary> Successors and predecessors for POP_TOP </summary>

|Predecessors | Count | Percentage | 
|---|---:|---:|
| RETURN_CONST | 47,915,520 | 90.2% |
| POP_JUMP_IF_FALSE | 2,314,240 | 4.4% |
| CALL | 1,579,920 | 3.0% |
| RETURN_VALUE | 770,480 | 1.5% |
| POP_JUMP_IF_TRUE | 512,000 | 1.0% |

|Successors | Count | Percentage | 
|---|---:|---:|
| JUMP_BACKWARD | 31,490,640 | 59.3% |
| LOAD_FAST | 9,326,080 | 17.6% |
| RETURN_CONST | 3,916,840 | 7.4% |
| LOAD_FAST_LOAD_FAST | 3,906,560 | 7.4% |
| LOAD_GLOBAL_BUILTIN | 2,603,360 | 4.9% |


</details>

### PUSH_NULL

<details>
<summary> Successors and predecessors for PUSH_NULL </summary>

|Predecessors | Count | Percentage | 
|---|---:|---:|
| LOAD_FAST | 2,720 | 94.4% |
| LOAD_DEREF | 80 | 2.8% |
| LOAD_ATTR_MODULE | 60 | 2.1% |
| LOAD_ATTR | 20 | 0.7% |

|Successors | Count | Percentage | 
|---|---:|---:|
| CALL | 2,800 | 97.2% |
| LOAD_FAST | 80 | 2.8% |


</details>

### RETURN_VALUE

<details>
<summary> Successors and predecessors for RETURN_VALUE </summary>

|Predecessors | Count | Percentage | 
|---|---:|---:|
| LOAD_ATTR_INSTANCE_VALUE | 67,089,780 | 82.0% |
| COMPARE_OP_INT | 9,277,380 | 11.3% |
| LOAD_FAST | 3,379,280 | 4.1% |
| EXIT_INIT_CHECK | 1,318,140 | 1.6% |
| POP_JUMP_IF_TRUE | 773,120 | 0.9% |

|Successors | Count | Percentage | 
|---|---:|---:|
| LOAD_ATTR_INSTANCE_VALUE | 28,710,280 | 35.1% |
| STORE_ATTR_INSTANCE_VALUE | 27,924,360 | 34.1% |
| TO_BOOL_BOOL | 10,395,620 | 12.7% |
| STORE_FAST | 8,867,700 | 10.8% |
| LOAD_FAST | 4,656,640 | 5.7% |


</details>

### TO_BOOL

<details>
<summary> Successors and predecessors for TO_BOOL </summary>

|Predecessors | Count | Percentage | 
|---|---:|---:|
| RETURN_VALUE | 540 | 42.2% |
| COPY | 160 | 12.5% |
| RETURN_CONST | 140 | 10.9% |
| CALL | 120 | 9.4% |
| CALL_LEN | 120 | 9.4% |

|Successors | Count | Percentage | 
|---|---:|---:|
| TO_BOOL_BOOL | 520 | 40.6% |
| POP_JUMP_IF_FALSE | 460 | 35.9% |
| POP_JUMP_IF_TRUE | 160 | 12.5% |
| TO_BOOL_INT | 120 | 9.4% |
| UNARY_NOT | 20 | 1.6% |


</details>

### UNARY_NOT

<details>
<summary> Successors and predecessors for UNARY_NOT </summary>

|Predecessors | Count | Percentage | 
|---|---:|---:|
| TO_BOOL_BOOL | 271,340 | 100.0% |
| TO_BOOL | 20 | 0.0% |

|Successors | Count | Percentage | 
|---|---:|---:|
| LOAD_FAST | 271,360 | 100.0% |


</details>

### BINARY_OP

<details>
<summary> Successors and predecessors for BINARY_OP </summary>

|Predecessors | Count | Percentage | 
|---|---:|---:|
| LOAD_FAST | 770,600 | 90.0% |
| LOAD_ATTR_INSTANCE_VALUE | 84,520 | 9.9% |
| BINARY_OP | 1,000 | 0.1% |
| LOAD_CONST | 320 | 0.0% |
| LOAD_ATTR | 80 | 0.0% |

|Successors | Count | Percentage | 
|---|---:|---:|
| LOAD_FAST | 596,540 | 69.6% |
| STORE_FAST | 258,580 | 30.2% |
| BINARY_OP | 1,000 | 0.1% |
| BINARY_OP_ADD_INT | 100 | 0.0% |
| CALL | 60 | 0.0% |


</details>

### BUILD_CONST_KEY_MAP

<details>
<summary> Successors and predecessors for BUILD_CONST_KEY_MAP </summary>

|Predecessors | Count | Percentage | 
|---|---:|---:|
| LOAD_CONST | 10,240 | 100.0% |

|Successors | Count | Percentage | 
|---|---:|---:|
| STORE_FAST | 10,240 | 100.0% |


</details>

### CALL

<details>
<summary> Successors and predecessors for CALL </summary>

|Predecessors | Count | Percentage | 
|---|---:|---:|
| LOAD_GLOBAL_MODULE | 2,134,920 | 53.6% |
| LOAD_SUPER_ATTR_METHOD | 1,576,900 | 39.6% |
| LOAD_FAST | 260,440 | 6.5% |
| CALL | 3,420 | 0.1% |
| PUSH_NULL | 2,800 | 0.1% |

|Successors | Count | Percentage | 
|---|---:|---:|
| STORE_FAST | 1,605,420 | 40.3% |
| POP_TOP | 1,579,920 | 39.7% |
| LOAD_FAST | 788,560 | 19.8% |
| CALL | 3,420 | 0.1% |
| CALL_PY_EXACT_ARGS | 1,520 | 0.0% |


</details>

### CALL_FUNCTION_EX

<details>
<summary> Successors and predecessors for CALL_FUNCTION_EX </summary>

|Predecessors | Count | Percentage | 
|---|---:|---:|
| LOAD_FAST | 80 | 100.0% |

|Successors | Count | Percentage | 
|---|---:|---:|
| COPY_FREE_VARS | 80 | 100.0% |


</details>

### COMPARE_OP

<details>
<summary> Successors and predecessors for COMPARE_OP </summary>

|Predecessors | Count | Percentage | 
|---|---:|---:|
| LOAD_FAST_LOAD_FAST | 5,470,760 | 99.2% |
| LOAD_FAST | 20,840 | 0.4% |
| LOAD_ATTR | 15,480 | 0.3% |
| LOAD_CONST | 2,680 | 0.0% |
| COMPARE_OP | 2,460 | 0.0% |

|Successors | Count | Percentage | 
|---|---:|---:|
| POP_JUMP_IF_TRUE | 5,470,780 | 99.2% |
| POP_JUMP_IF_FALSE | 28,440 | 0.5% |
| STORE_FAST | 10,240 | 0.2% |
| COMPARE_OP | 2,460 | 0.0% |
| COMPARE_OP_INT | 420 | 0.0% |


</details>

### COPY

<details>
<summary> Successors and predecessors for COPY </summary>

|Predecessors | Count | Percentage | 
|---|---:|---:|
| LOAD_ATTR_INSTANCE_VALUE | 3,087,300 | 66.3% |
| LOAD_FAST | 796,160 | 17.1% |
| COMPARE_OP_INT | 773,100 | 16.6% |
| LOAD_ATTR | 60 | 0.0% |
| COMPARE_OP | 20 | 0.0% |

|Successors | Count | Percentage | 
|---|---:|---:|
| TO_BOOL_BOOL | 3,860,320 | 82.9% |
| LOAD_ATTR_INSTANCE_VALUE | 796,120 | 17.1% |
| TO_BOOL | 160 | 0.0% |
| LOAD_ATTR | 40 | 0.0% |


</details>

### COPY_FREE_VARS

<details>
<summary> Successors and predecessors for COPY_FREE_VARS </summary>

|Predecessors | Count | Percentage | 
|---|---:|---:|
| CALL_PY_EXACT_ARGS | 1,825,180 | 53.6% |
| CALL_ALLOC_AND_ENTER_INIT | 1,318,140 | 38.7% |
| CACHE | 258,820 | 7.6% |
| CALL | 100 | 0.0% |
| CALL_FUNCTION_EX | 80 | 0.0% |

|Successors | Count | Percentage | 
|---|---:|---:|
| RESUME_CHECK | 3,402,080 | 100.0% |
| RESUME | 240 | 0.0% |


</details>

### FOR_ITER

<details>
<summary> Successors and predecessors for FOR_ITER </summary>

|Predecessors | Count | Percentage | 
|---|---:|---:|
| GET_ITER | 260 | 50.0% |
| JUMP_BACKWARD | 260 | 50.0% |

|Successors | Count | Percentage | 
|---|---:|---:|
| STORE_FAST | 260 | 50.0% |
| FOR_ITER_RANGE | 140 | 26.9% |
| FOR_ITER_LIST | 120 | 23.1% |


</details>

### JUMP_BACKWARD

<details>
<summary> Successors and predecessors for JUMP_BACKWARD </summary>

|Predecessors | Count | Percentage | 
|---|---:|---:|
| POP_TOP | 31,490,640 | 76.1% |
| POP_JUMP_IF_TRUE | 4,428,800 | 10.7% |
| POP_JUMP_IF_FALSE | 2,839,040 | 6.9% |
| CALL_LIST_APPEND | 1,827,760 | 4.4% |
| POP_JUMP_IF_NONE | 509,440 | 1.2% |

|Successors | Count | Percentage | 
|---|---:|---:|
| FOR_ITER_LIST | 37,667,720 | 91.1% |
| LOAD_FAST | 2,314,240 | 5.6% |
| FOR_ITER_RANGE | 1,382,260 | 3.3% |
| FOR_ITER | 260 | 0.0% |


</details>

### JUMP_FORWARD

<details>
<summary> Successors and predecessors for JUMP_FORWARD </summary>

|Predecessors | Count | Percentage | 
|---|---:|---:|
| STORE_ATTR_INSTANCE_VALUE | 514,520 | 100.0% |
| STORE_ATTR | 40 | 0.0% |

|Successors | Count | Percentage | 
|---|---:|---:|
| LOAD_GLOBAL_MODULE | 258,560 | 50.2% |
| LOAD_FAST | 256,000 | 49.8% |


</details>

### LOAD_ATTR

<details>
<summary> Successors and predecessors for LOAD_ATTR </summary>

|Predecessors | Count | Percentage | 
|---|---:|---:|
| LOAD_FAST | 8,594,160 | 48.4% |
| LOAD_GLOBAL_MODULE | 6,492,160 | 36.5% |
| LOAD_ATTR_INSTANCE_VALUE | 2,604,000 | 14.7% |
| LOAD_ATTR_SLOT | 61,320 | 0.3% |
| LOAD_ATTR | 12,160 | 0.1% |

|Successors | Count | Percentage | 
|---|---:|---:|
| LOAD_FAST | 11,743,860 | 66.1% |
| LOAD_CONST | 3,136,060 | 17.7% |
| LOAD_FAST_LOAD_FAST | 2,058,260 | 11.6% |
| CALL_ALLOC_AND_ENTER_INIT | 783,120 | 4.4% |
| COMPARE_OP | 15,480 | 0.1% |


</details>

### LOAD_CONST

<details>
<summary> Successors and predecessors for LOAD_CONST </summary>

|Predecessors | Count | Percentage | 
|---|---:|---:|
| LOAD_ATTR | 3,136,060 | 33.9% |
| STORE_ATTR_INSTANCE_VALUE | 2,608,480 | 28.2% |
| LOAD_ATTR_INSTANCE_VALUE | 801,220 | 8.7% |
| LOAD_FAST | 783,440 | 8.5% |
| LOAD_GLOBAL_MODULE | 517,040 | 5.6% |

|Successors | Count | Percentage | 
|---|---:|---:|
| LOAD_FAST | 3,978,240 | 43.0% |
| CALL_METHOD_DESCRIPTOR_FAST | 3,125,640 | 33.8% |
| BINARY_OP_ADD_INT | 1,305,440 | 14.1% |
| BINARY_OP_MULTIPLY_INT | 506,800 | 5.5% |
| COMPARE_OP_INT | 261,080 | 2.8% |


</details>

### LOAD_DEREF

<details>
<summary> Successors and predecessors for LOAD_DEREF </summary>

|Predecessors | Count | Percentage | 
|---|---:|---:|
| NOP | 80 | 50.0% |
| STORE_FAST | 80 | 50.0% |

|Successors | Count | Percentage | 
|---|---:|---:|
| PUSH_NULL | 80 | 50.0% |
| STORE_FAST | 80 | 50.0% |


</details>

### LOAD_FAST

<details>
<summary> Successors and predecessors for LOAD_FAST </summary>

|Predecessors | Count | Percentage | 
|---|---:|---:|
| RESUME_CHECK | 124,154,240 | 31.7% |
| POP_JUMP_IF_FALSE | 81,198,080 | 20.7% |
| LOAD_ATTR_INSTANCE_VALUE | 50,917,820 | 13.0% |
| STORE_FAST | 50,457,920 | 12.9% |
| LOAD_ATTR | 11,743,860 | 3.0% |

|Successors | Count | Percentage | 
|---|---:|---:|
| LOAD_ATTR_INSTANCE_VALUE | 210,659,280 | 53.8% |
| LOAD_ATTR_METHOD_WITH_VALUES | 115,525,680 | 29.5% |
| STORE_ATTR_INSTANCE_VALUE | 12,233,020 | 3.1% |
| CALL_PY_EXACT_ARGS | 12,023,280 | 3.1% |
| LOAD_ATTR | 8,594,160 | 2.2% |


</details>

### LOAD_FAST_CHECK

<details>
<summary> Successors and predecessors for LOAD_FAST_CHECK </summary>

|Predecessors | Count | Percentage | 
|---|---:|---:|
| POP_TOP | 2,560 | 100.0% |

|Successors | Count | Percentage | 
|---|---:|---:|
| LOAD_ATTR_INSTANCE_VALUE | 2,520 | 98.4% |
| LOAD_ATTR | 40 | 1.6% |


</details>

### LOAD_FAST_LOAD_FAST

<details>
<summary> Successors and predecessors for LOAD_FAST_LOAD_FAST </summary>

|Predecessors | Count | Percentage | 
|---|---:|---:|
| STORE_FAST | 6,348,800 | 31.2% |
| POP_TOP | 3,906,560 | 19.2% |
| LOAD_ATTR | 2,058,260 | 10.1% |
| STORE_ATTR_INSTANCE_VALUE | 2,058,140 | 10.1% |
| POP_JUMP_IF_TRUE | 1,297,920 | 6.4% |

|Successors | Count | Percentage | 
|---|---:|---:|
| STORE_ATTR_INSTANCE_VALUE | 7,095,780 | 34.9% |
| COMPARE_OP | 5,470,760 | 26.9% |
| CALL_BOUND_METHOD_EXACT_ARGS | 2,058,200 | 10.1% |
| LOAD_ATTR_METHOD_WITH_VALUES | 1,812,400 | 8.9% |
| CALL_PY_EXACT_ARGS | 1,569,160 | 7.7% |


</details>

### LOAD_GLOBAL

<details>
<summary> Successors and predecessors for LOAD_GLOBAL </summary>

|Predecessors | Count | Percentage | 
|---|---:|---:|
| STORE_FAST | 680 | 16.7% |
| POP_JUMP_IF_FALSE | 560 | 13.7% |
| POP_TOP | 500 | 12.3% |
| RESUME | 380 | 9.3% |
| RESUME_CHECK | 380 | 9.3% |

|Successors | Count | Percentage | 
|---|---:|---:|
| LOAD_GLOBAL_MODULE | 1,560 | 38.2% |
| LOAD_ATTR | 760 | 18.6% |
| LOAD_FAST | 660 | 16.2% |
| LOAD_GLOBAL_BUILTIN | 480 | 11.8% |
| CALL | 240 | 5.9% |


</details>

### LOAD_SUPER_ATTR

<details>
<summary> Successors and predecessors for LOAD_SUPER_ATTR </summary>

|Predecessors | Count | Percentage | 
|---|---:|---:|
| LOAD_FAST | 440 | 100.0% |

|Successors | Count | Percentage | 
|---|---:|---:|
| LOAD_SUPER_ATTR_METHOD | 220 | 50.0% |
| CALL | 100 | 22.7% |
| LOAD_FAST | 60 | 13.6% |
| LOAD_FAST_LOAD_FAST | 60 | 13.6% |


</details>

### POP_JUMP_IF_FALSE

<details>
<summary> Successors and predecessors for POP_JUMP_IF_FALSE </summary>

|Predecessors | Count | Percentage | 
|---|---:|---:|
| COMPARE_OP_INT | 76,991,800 | 82.7% |
| TO_BOOL_BOOL | 11,663,020 | 12.5% |
| TO_BOOL_INT | 4,446,600 | 4.8% |
| COMPARE_OP | 28,440 | 0.0% |
| TO_BOOL | 460 | 0.0% |

|Successors | Count | Percentage | 
|---|---:|---:|
| LOAD_FAST | 81,198,080 | 87.2% |
| LOAD_GLOBAL_MODULE | 4,136,440 | 4.4% |
| JUMP_BACKWARD | 2,839,040 | 3.0% |
| POP_TOP | 2,314,240 | 2.5% |
| RETURN_CONST | 2,099,200 | 2.3% |


</details>

### POP_JUMP_IF_NONE

<details>
<summary> Successors and predecessors for POP_JUMP_IF_NONE </summary>

|Predecessors | Count | Percentage | 
|---|---:|---:|
| LOAD_FAST | 2,859,520 | 99.6% |
| LOAD_ATTR_INSTANCE_VALUE | 10,220 | 0.4% |
| LOAD_ATTR | 20 | 0.0% |

|Successors | Count | Percentage | 
|---|---:|---:|
| RETURN_CONST | 783,360 | 27.3% |
| LOAD_FAST_LOAD_FAST | 778,240 | 27.1% |
| LOAD_FAST | 542,720 | 18.9% |
| JUMP_BACKWARD | 509,440 | 17.8% |
| LOAD_GLOBAL_MODULE | 255,960 | 8.9% |


</details>

### POP_JUMP_IF_TRUE

<details>
<summary> Successors and predecessors for POP_JUMP_IF_TRUE </summary>

|Predecessors | Count | Percentage | 
|---|---:|---:|
| TO_BOOL_BOOL | 6,266,720 | 50.1% |
| COMPARE_OP | 5,470,780 | 43.8% |
| COMPARE_OP_INT | 762,820 | 6.1% |
| TO_BOOL | 160 | 0.0% |

|Successors | Count | Percentage | 
|---|---:|---:|
| LOAD_FAST | 5,488,640 | 43.9% |
| JUMP_BACKWARD | 4,428,800 | 35.4% |
| LOAD_FAST_LOAD_FAST | 1,297,920 | 10.4% |
| RETURN_VALUE | 773,120 | 6.2% |
| POP_TOP | 512,000 | 4.1% |


</details>

### RETURN_CONST

<details>
<summary> Successors and predecessors for RETURN_CONST </summary>

|Predecessors | Count | Percentage | 
|---|---:|---:|
| STORE_ATTR_INSTANCE_VALUE | 37,554,820 | 73.5% |
| POP_TOP | 3,916,840 | 7.7% |
| FOR_ITER_LIST | 2,956,800 | 5.8% |
| CALL_LIST_APPEND | 2,593,240 | 5.1% |
| POP_JUMP_IF_FALSE | 2,099,200 | 4.1% |

|Successors | Count | Percentage | 
|---|---:|---:|
| POP_TOP | 47,915,520 | 93.8% |
| TO_BOOL_BOOL | 1,594,740 | 3.1% |
| EXIT_INIT_CHECK | 1,318,140 | 2.6% |
| INTERPRETER_EXIT | 261,380 | 0.5% |
| STORE_FAST | 5,120 | 0.0% |


</details>

### STORE_ATTR

<details>
<summary> Successors and predecessors for STORE_ATTR </summary>

|Predecessors | Count | Percentage | 
|---|---:|---:|
| LOAD_FAST | 1,220 | 55.5% |
| LOAD_FAST_LOAD_FAST | 540 | 24.5% |
| RETURN_VALUE | 120 | 5.5% |
| LOAD_ATTR | 120 | 5.5% |
| LOAD_ATTR_INSTANCE_VALUE | 120 | 5.5% |

|Successors | Count | Percentage | 
|---|---:|---:|
| STORE_ATTR_INSTANCE_VALUE | 1,020 | 46.4% |
| RETURN_CONST | 380 | 17.3% |
| LOAD_FAST | 320 | 14.5% |
| LOAD_CONST | 160 | 7.3% |
| LOAD_GLOBAL | 140 | 6.4% |


</details>

### STORE_FAST

<details>
<summary> Successors and predecessors for STORE_FAST </summary>

|Predecessors | Count | Percentage | 
|---|---:|---:|
| FOR_ITER_LIST | 37,667,720 | 62.5% |
| RETURN_VALUE | 8,867,700 | 14.7% |
| LOAD_ATTR_INSTANCE_VALUE | 7,022,000 | 11.7% |
| CALL_METHOD_DESCRIPTOR_FAST | 3,125,700 | 5.2% |
| CALL | 1,605,420 | 2.7% |

|Successors | Count | Percentage | 
|---|---:|---:|
| LOAD_FAST | 50,457,920 | 83.7% |
| LOAD_FAST_LOAD_FAST | 6,348,800 | 10.5% |
| LOAD_GLOBAL_MODULE | 2,879,520 | 4.8% |
| LOAD_CONST | 271,360 | 0.5% |
| JUMP_BACKWARD | 268,800 | 0.4% |


</details>

### STORE_FAST_STORE_FAST

<details>
<summary> Successors and predecessors for STORE_FAST_STORE_FAST </summary>

|Predecessors | Count | Percentage | 
|---|---:|---:|
| UNPACK_SEQUENCE_TUPLE | 2,540 | 99.2% |
| UNPACK_SEQUENCE | 20 | 0.8% |

|Successors | Count | Percentage | 
|---|---:|---:|
| STORE_FAST | 2,560 | 100.0% |


</details>

### STORE_GLOBAL

<details>
<summary> Successors and predecessors for STORE_GLOBAL </summary>

|Predecessors | Count | Percentage | 
|---|---:|---:|
| RETURN_VALUE | 5,080 | 99.2% |
| CALL | 40 | 0.8% |

|Successors | Count | Percentage | 
|---|---:|---:|
| LOAD_CONST | 2,560 | 50.0% |
| LOAD_GLOBAL_MODULE | 2,520 | 49.2% |
| LOAD_GLOBAL | 40 | 0.8% |


</details>

### SWAP

<details>
<summary> Successors and predecessors for SWAP </summary>

|Predecessors | Count | Percentage | 
|---|---:|---:|
| BINARY_OP_ADD_INT | 796,140 | 100.0% |
| BINARY_OP | 20 | 0.0% |

|Successors | Count | Percentage | 
|---|---:|---:|
| STORE_ATTR_INSTANCE_VALUE | 796,120 | 100.0% |
| STORE_ATTR | 40 | 0.0% |


</details>

### UNPACK_SEQUENCE

<details>
<summary> Successors and predecessors for UNPACK_SEQUENCE </summary>

|Predecessors | Count | Percentage | 
|---|---:|---:|
| LOAD_CONST | 40 | 100.0% |

|Successors | Count | Percentage | 
|---|---:|---:|
| STORE_FAST_STORE_FAST | 20 | 50.0% |
| UNPACK_SEQUENCE_TUPLE | 20 | 50.0% |


</details>

### RESUME

<details>
<summary> Successors and predecessors for RESUME </summary>

|Predecessors | Count | Percentage | 
|---|---:|---:|
| CALL | 740 | 61.7% |
| COPY_FREE_VARS | 240 | 20.0% |
| CALL_PY_EXACT_ARGS | 200 | 16.7% |
| CACHE | 20 | 1.7% |

|Successors | Count | Percentage | 
|---|---:|---:|
| LOAD_FAST | 640 | 53.3% |
| LOAD_GLOBAL | 380 | 31.7% |
| RETURN_CONST | 120 | 10.0% |
| LOAD_CONST | 40 | 3.3% |
| LOAD_FAST_LOAD_FAST | 20 | 1.7% |


</details>

### BINARY_OP_ADD_INT

<details>
<summary> Successors and predecessors for BINARY_OP_ADD_INT </summary>

|Predecessors | Count | Percentage | 
|---|---:|---:|
| LOAD_ATTR_INSTANCE_VALUE | 5,859,800 | 81.8% |
| LOAD_CONST | 1,305,440 | 18.2% |
| BINARY_OP | 100 | 0.0% |

|Successors | Count | Percentage | 
|---|---:|---:|
| LOAD_FAST | 5,859,820 | 81.8% |
| SWAP | 796,140 | 11.1% |
| COMPARE_OP_INT | 506,800 | 7.1% |
| CALL_BUILTIN_CLASS | 2,520 | 0.0% |
| COMPARE_OP | 40 | 0.0% |


</details>

### BINARY_OP_MULTIPLY_INT

<details>
<summary> Successors and predecessors for BINARY_OP_MULTIPLY_INT </summary>

|Predecessors | Count | Percentage | 
|---|---:|---:|
| LOAD_ATTR_INSTANCE_VALUE | 5,859,800 | 92.0% |
| LOAD_CONST | 506,800 | 8.0% |
| BINARY_OP | 60 | 0.0% |

|Successors | Count | Percentage | 
|---|---:|---:|
| LOAD_FAST | 5,859,820 | 92.0% |
| LOAD_CONST | 506,840 | 8.0% |


</details>

### BINARY_OP_SUBTRACT_FLOAT

<details>
<summary> Successors and predecessors for BINARY_OP_SUBTRACT_FLOAT </summary>

|Predecessors | Count | Percentage | 
|---|---:|---:|
| LOAD_FAST | 40 | 66.7% |
| BINARY_OP | 20 | 33.3% |

|Successors | Count | Percentage | 
|---|---:|---:|
| STORE_FAST | 60 | 100.0% |


</details>

### BINARY_OP_SUBTRACT_INT

<details>
<summary> Successors and predecessors for BINARY_OP_SUBTRACT_INT </summary>

|Predecessors | Count | Percentage | 
|---|---:|---:|
| LOAD_ATTR_INSTANCE_VALUE | 84,440 | 94.3% |
| LOAD_CONST | 5,040 | 5.6% |
| BINARY_OP | 60 | 0.1% |

|Successors | Count | Percentage | 
|---|---:|---:|
| LOAD_FAST | 84,460 | 94.3% |
| CALL_BUILTIN_CLASS | 5,040 | 5.6% |
| CALL | 40 | 0.0% |


</details>

### BINARY_SUBSCR_DICT

<details>
<summary> Successors and predecessors for BINARY_SUBSCR_DICT </summary>

|Predecessors | Count | Percentage | 
|---|---:|---:|
| LOAD_ATTR_INSTANCE_VALUE | 10,200 | 99.8% |
| BINARY_SUBSCR | 20 | 0.2% |

|Successors | Count | Percentage | 
|---|---:|---:|
| RETURN_VALUE | 10,220 | 100.0% |


</details>

### CALL_ALLOC_AND_ENTER_INIT

<details>
<summary> Successors and predecessors for CALL_ALLOC_AND_ENTER_INIT </summary>

|Predecessors | Count | Percentage | 
|---|---:|---:|
| LOAD_ATTR | 783,120 | 59.4% |
| LOAD_FAST | 511,920 | 38.8% |
| LOAD_GLOBAL_MODULE | 17,800 | 1.4% |
| LOAD_CONST | 5,040 | 0.4% |
| CALL | 260 | 0.0% |

|Successors | Count | Percentage | 
|---|---:|---:|
| COPY_FREE_VARS | 1,318,140 | 100.0% |


</details>

### CALL_BOUND_METHOD_EXACT_ARGS

<details>
<summary> Successors and predecessors for CALL_BOUND_METHOD_EXACT_ARGS </summary>

|Predecessors | Count | Percentage | 
|---|---:|---:|
| LOAD_ATTR_INSTANCE_VALUE | 4,896,960 | 70.4% |
| LOAD_FAST_LOAD_FAST | 2,058,200 | 29.6% |
| CALL | 180 | 0.0% |

|Successors | Count | Percentage | 
|---|---:|---:|
| RESUME_CHECK | 6,955,340 | 100.0% |


</details>

### CALL_BUILTIN_CLASS

<details>
<summary> Successors and predecessors for CALL_BUILTIN_CLASS </summary>

|Predecessors | Count | Percentage | 
|---|---:|---:|
| LOAD_CONST | 12,720 | 55.4% |
| BINARY_OP_SUBTRACT_INT | 5,040 | 21.9% |
| LOAD_FAST | 2,560 | 11.1% |
| BINARY_OP_ADD_INT | 2,520 | 11.0% |
| CALL | 140 | 0.6% |

|Successors | Count | Percentage | 
|---|---:|---:|
| GET_ITER | 22,920 | 99.7% |
| STORE_FAST | 60 | 0.3% |


</details>

### CALL_LEN

<details>
<summary> Successors and predecessors for CALL_LEN </summary>

|Predecessors | Count | Percentage | 
|---|---:|---:|
| LOAD_FAST | 4,446,480 | 100.0% |
| CALL | 120 | 0.0% |

|Successors | Count | Percentage | 
|---|---:|---:|
| TO_BOOL_INT | 4,446,480 | 100.0% |
| TO_BOOL | 120 | 0.0% |


</details>

### CALL_LIST_APPEND

<details>
<summary> Successors and predecessors for CALL_LIST_APPEND </summary>

|Predecessors | Count | Percentage | 
|---|---:|---:|
| LOAD_FAST | 5,480,560 | 91.4% |
| RETURN_VALUE | 517,080 | 8.6% |
| CALL | 220 | 0.0% |

|Successors | Count | Percentage | 
|---|---:|---:|
| RETURN_CONST | 2,593,240 | 43.2% |
| JUMP_BACKWARD | 1,827,760 | 30.5% |
| LOAD_GLOBAL_BUILTIN | 1,308,080 | 21.8% |
| LOAD_GLOBAL_MODULE | 268,680 | 4.5% |
| LOAD_GLOBAL | 100 | 0.0% |


</details>

### CALL_METHOD_DESCRIPTOR_FAST

<details>
<summary> Successors and predecessors for CALL_METHOD_DESCRIPTOR_FAST </summary>

|Predecessors | Count | Percentage | 
|---|---:|---:|
| LOAD_CONST | 3,125,640 | 98.1% |
| CALL_METHOD_DESCRIPTOR_FAST | 60,080 | 1.9% |
| CALL | 60 | 0.0% |

|Successors | Count | Percentage | 
|---|---:|---:|
| STORE_FAST | 3,125,700 | 98.1% |
| CALL_METHOD_DESCRIPTOR_FAST | 60,080 | 1.9% |


</details>

### CALL_METHOD_DESCRIPTOR_O

<details>
<summary> Successors and predecessors for CALL_METHOD_DESCRIPTOR_O </summary>

|Predecessors | Count | Percentage | 
|---|---:|---:|
| LOAD_FAST | 10,200 | 98.1% |
| CALL_METHOD_DESCRIPTOR_O | 180 | 1.7% |
| CALL | 20 | 0.2% |

|Successors | Count | Percentage | 
|---|---:|---:|
| POP_TOP | 10,220 | 98.3% |
| CALL_METHOD_DESCRIPTOR_O | 180 | 1.7% |


</details>

### CALL_PY_EXACT_ARGS

<details>
<summary> Successors and predecessors for CALL_PY_EXACT_ARGS </summary>

|Predecessors | Count | Percentage | 
|---|---:|---:|
| LOAD_ATTR_METHOD_WITH_VALUES | 109,241,200 | 88.7% |
| LOAD_FAST | 12,023,280 | 9.8% |
| LOAD_FAST_LOAD_FAST | 1,569,160 | 1.3% |
| LOAD_SUPER_ATTR_METHOD | 255,960 | 0.2% |
| CALL_PY_EXACT_ARGS | 65,480 | 0.1% |

|Successors | Count | Percentage | 
|---|---:|---:|
| RESUME_CHECK | 121,275,820 | 98.5% |
| COPY_FREE_VARS | 1,825,180 | 1.5% |
| CALL_PY_EXACT_ARGS | 65,480 | 0.1% |
| RESUME | 200 | 0.0% |


</details>

### COMPARE_OP_INT

<details>
<summary> Successors and predecessors for COMPARE_OP_INT </summary>

|Predecessors | Count | Percentage | 
|---|---:|---:|
| LOAD_ATTR_CLASS | 75,409,760 | 85.9% |
| LOAD_FAST | 6,471,320 | 7.4% |
| LOAD_ATTR_INSTANCE_VALUE | 4,897,200 | 5.6% |
| BINARY_OP_ADD_INT | 506,800 | 0.6% |
| LOAD_CONST | 261,080 | 0.3% |

|Successors | Count | Percentage | 
|---|---:|---:|
| POP_JUMP_IF_FALSE | 76,991,800 | 87.7% |
| RETURN_VALUE | 9,277,380 | 10.6% |
| COPY | 773,100 | 0.9% |
| POP_JUMP_IF_TRUE | 762,820 | 0.9% |


</details>

### FOR_ITER_LIST

<details>
<summary> Successors and predecessors for FOR_ITER_LIST </summary>

|Predecessors | Count | Percentage | 
|---|---:|---:|
| JUMP_BACKWARD | 37,667,720 | 90.3% |
| GET_ITER | 4,034,440 | 9.7% |
| FOR_ITER | 120 | 0.0% |

|Successors | Count | Percentage | 
|---|---:|---:|
| STORE_FAST | 37,667,720 | 90.3% |
| RETURN_CONST | 2,956,800 | 7.1% |
| LOAD_FAST | 550,400 | 1.3% |
| LOAD_GLOBAL_BUILTIN | 527,320 | 1.3% |
| LOAD_GLOBAL | 40 | 0.0% |


</details>

### FOR_ITER_RANGE

<details>
<summary> Successors and predecessors for FOR_ITER_RANGE </summary>

|Predecessors | Count | Percentage | 
|---|---:|---:|
| JUMP_BACKWARD | 1,382,260 | 98.4% |
| GET_ITER | 22,980 | 1.6% |
| FOR_ITER | 140 | 0.0% |

|Successors | Count | Percentage | 
|---|---:|---:|
| STORE_FAST | 1,382,260 | 98.4% |
| LOAD_FAST | 10,320 | 0.7% |
| LOAD_GLOBAL_MODULE | 7,560 | 0.5% |
| RETURN_CONST | 5,120 | 0.4% |
| LOAD_GLOBAL | 120 | 0.0% |


</details>

### LOAD_ATTR_CLASS

<details>
<summary> Successors and predecessors for LOAD_ATTR_CLASS </summary>

|Predecessors | Count | Percentage | 
|---|---:|---:|
| LOAD_GLOBAL_MODULE | 78,745,120 | 100.0% |
| LOAD_ATTR | 240 | 0.0% |

|Successors | Count | Percentage | 
|---|---:|---:|
| COMPARE_OP_INT | 75,409,760 | 95.8% |
| LOAD_FAST | 3,335,520 | 4.2% |
| COMPARE_OP | 80 | 0.0% |


</details>

### LOAD_ATTR_INSTANCE_VALUE

<details>
<summary> Successors and predecessors for LOAD_ATTR_INSTANCE_VALUE </summary>

|Predecessors | Count | Percentage | 
|---|---:|---:|
| LOAD_FAST | 210,659,280 | 78.5% |
| RETURN_VALUE | 28,710,280 | 10.7% |
| LOAD_ATTR_INSTANCE_VALUE | 27,204,200 | 10.1% |
| COPY | 796,120 | 0.3% |
| LOAD_FAST_LOAD_FAST | 527,240 | 0.2% |

|Successors | Count | Percentage | 
|---|---:|---:|
| LOAD_GLOBAL_MODULE | 75,414,840 | 28.1% |
| RETURN_VALUE | 67,089,780 | 25.0% |
| LOAD_FAST | 50,917,820 | 19.0% |
| LOAD_ATTR_INSTANCE_VALUE | 27,204,200 | 10.1% |
| STORE_FAST | 7,022,000 | 2.6% |


</details>

### LOAD_ATTR_METHOD_WITH_VALUES

<details>
<summary> Successors and predecessors for LOAD_ATTR_METHOD_WITH_VALUES </summary>

|Predecessors | Count | Percentage | 
|---|---:|---:|
| LOAD_FAST | 115,525,680 | 95.2% |
| LOAD_GLOBAL_MODULE | 2,104,120 | 1.7% |
| LOAD_ATTR_INSTANCE_VALUE | 1,817,360 | 1.5% |
| LOAD_FAST_LOAD_FAST | 1,812,400 | 1.5% |
| LOAD_ATTR_METHOD_WITH_VALUES | 124,720 | 0.1% |

|Successors | Count | Percentage | 
|---|---:|---:|
| CALL_PY_EXACT_ARGS | 109,241,200 | 90.0% |
| LOAD_FAST | 10,720,880 | 8.8% |
| LOAD_FAST_LOAD_FAST | 1,297,900 | 1.1% |
| LOAD_ATTR_METHOD_WITH_VALUES | 124,720 | 0.1% |
| CALL | 840 | 0.0% |


</details>

### LOAD_ATTR_MODULE

<details>
<summary> Successors and predecessors for LOAD_ATTR_MODULE </summary>

|Predecessors | Count | Percentage | 
|---|---:|---:|
| LOAD_GLOBAL_MODULE | 80 | 66.7% |
| LOAD_ATTR | 40 | 33.3% |

|Successors | Count | Percentage | 
|---|---:|---:|
| PUSH_NULL | 60 | 50.0% |
| STORE_FAST | 60 | 50.0% |


</details>

### LOAD_ATTR_SLOT

<details>
<summary> Successors and predecessors for LOAD_ATTR_SLOT </summary>

|Predecessors | Count | Percentage | 
|---|---:|---:|
| LOAD_FAST | 61,200 | 99.8% |
| LOAD_ATTR | 120 | 0.2% |

|Successors | Count | Percentage | 
|---|---:|---:|
| LOAD_ATTR | 61,320 | 100.0% |


</details>

### LOAD_GLOBAL_BUILTIN

<details>
<summary> Successors and predecessors for LOAD_GLOBAL_BUILTIN </summary>

|Predecessors | Count | Percentage | 
|---|---:|---:|
| RESUME_CHECK | 3,145,840 | 40.0% |
| POP_TOP | 2,603,360 | 33.1% |
| CALL_LIST_APPEND | 1,308,080 | 16.6% |
| FOR_ITER_LIST | 527,320 | 6.7% |
| STORE_ATTR_INSTANCE_VALUE | 255,960 | 3.3% |

|Successors | Count | Percentage | 
|---|---:|---:|
| LOAD_FAST | 4,456,820 | 56.6% |
| LOAD_GLOBAL_MODULE | 3,401,800 | 43.2% |
| LOAD_CONST | 12,760 | 0.2% |
| LOAD_GLOBAL | 220 | 0.0% |


</details>

### LOAD_GLOBAL_MODULE

<details>
<summary> Successors and predecessors for LOAD_GLOBAL_MODULE </summary>

|Predecessors | Count | Percentage | 
|---|---:|---:|
| LOAD_ATTR_INSTANCE_VALUE | 75,414,840 | 79.8% |
| POP_JUMP_IF_FALSE | 4,136,440 | 4.4% |
| LOAD_GLOBAL_BUILTIN | 3,401,800 | 3.6% |
| STORE_ATTR_INSTANCE_VALUE | 3,381,520 | 3.6% |
| STORE_FAST | 2,879,520 | 3.0% |

|Successors | Count | Percentage | 
|---|---:|---:|
| LOAD_ATTR_CLASS | 78,745,120 | 83.4% |
| LOAD_ATTR | 6,492,160 | 6.9% |
| LOAD_FAST | 3,947,080 | 4.2% |
| CALL | 2,134,920 | 2.3% |
| LOAD_ATTR_METHOD_WITH_VALUES | 2,104,120 | 2.2% |


</details>

### LOAD_SUPER_ATTR_METHOD

<details>
<summary> Successors and predecessors for LOAD_SUPER_ATTR_METHOD </summary>

|Predecessors | Count | Percentage | 
|---|---:|---:|
| LOAD_FAST | 3,401,800 | 100.0% |
| LOAD_SUPER_ATTR | 220 | 0.0% |

|Successors | Count | Percentage | 
|---|---:|---:|
| CALL | 1,576,900 | 46.4% |
| LOAD_FAST | 1,041,860 | 30.6% |
| LOAD_FAST_LOAD_FAST | 527,300 | 15.5% |
| CALL_PY_EXACT_ARGS | 255,960 | 7.5% |


</details>

### RESUME_CHECK

<details>
<summary> Successors and predecessors for RESUME_CHECK </summary>

|Predecessors | Count | Percentage | 
|---|---:|---:|
| CALL_PY_EXACT_ARGS | 121,275,820 | 92.1% |
| CALL_BOUND_METHOD_EXACT_ARGS | 6,955,340 | 5.3% |
| COPY_FREE_VARS | 3,402,080 | 2.6% |
| CACHE | 2,540 | 0.0% |
| CALL | 860 | 0.0% |

|Successors | Count | Percentage | 
|---|---:|---:|
| LOAD_FAST | 124,154,240 | 94.3% |
| LOAD_GLOBAL_BUILTIN | 3,145,840 | 2.4% |
| LOAD_GLOBAL_MODULE | 2,098,920 | 1.6% |
| RETURN_CONST | 1,185,160 | 0.9% |
| LOAD_FAST_LOAD_FAST | 1,026,540 | 0.8% |


</details>

### STORE_ATTR_INSTANCE_VALUE

<details>
<summary> Successors and predecessors for STORE_ATTR_INSTANCE_VALUE </summary>

|Predecessors | Count | Percentage | 
|---|---:|---:|
| RETURN_VALUE | 27,924,360 | 50.7% |
| LOAD_FAST | 12,233,020 | 22.2% |
| LOAD_FAST_LOAD_FAST | 7,095,780 | 12.9% |
| LOAD_ATTR_INSTANCE_VALUE | 7,003,920 | 12.7% |
| SWAP | 796,120 | 1.4% |

|Successors | Count | Percentage | 
|---|---:|---:|
| RETURN_CONST | 37,554,820 | 68.2% |
| LOAD_FAST | 8,680,640 | 15.8% |
| LOAD_GLOBAL_MODULE | 3,381,520 | 6.1% |
| LOAD_CONST | 2,608,480 | 4.7% |
| LOAD_FAST_LOAD_FAST | 2,058,140 | 3.7% |


</details>

### TO_BOOL_BOOL

<details>
<summary> Successors and predecessors for TO_BOOL_BOOL </summary>

|Predecessors | Count | Percentage | 
|---|---:|---:|
| RETURN_VALUE | 10,395,620 | 57.1% |
| COPY | 3,860,320 | 21.2% |
| LOAD_ATTR_INSTANCE_VALUE | 2,329,480 | 12.8% |
| RETURN_CONST | 1,594,740 | 8.8% |
| LOAD_FAST | 20,400 | 0.1% |

|Successors | Count | Percentage | 
|---|---:|---:|
| POP_JUMP_IF_FALSE | 11,663,020 | 64.1% |
| POP_JUMP_IF_TRUE | 6,266,720 | 34.4% |
| UNARY_NOT | 271,340 | 1.5% |


</details>

### TO_BOOL_INT

<details>
<summary> Successors and predecessors for TO_BOOL_INT </summary>

|Predecessors | Count | Percentage | 
|---|---:|---:|
| CALL_LEN | 4,446,480 | 100.0% |
| TO_BOOL | 120 | 0.0% |

|Successors | Count | Percentage | 
|---|---:|---:|
| POP_JUMP_IF_FALSE | 4,446,600 | 100.0% |


</details>

### UNPACK_SEQUENCE_TUPLE

<details>
<summary> Successors and predecessors for UNPACK_SEQUENCE_TUPLE </summary>

|Predecessors | Count | Percentage | 
|---|---:|---:|
| LOAD_CONST | 2,520 | 99.2% |
| UNPACK_SEQUENCE | 20 | 0.8% |

|Successors | Count | Percentage | 
|---|---:|---:|
| STORE_FAST_STORE_FAST | 2,540 | 100.0% |


</details>


</details>

## Specialization stats

<details>
<summary> specialization stats by family </summary>

### BINARY_OP

<details>
<summary> specialization stats for BINARY_OP family </summary>

|Kind | Count | Ratio | 
|---|---:|---:|
|     deferred | 855,280 | 5.9% |
|          hit | 13,621,600 | 94.1% |

| | Count | Ratio | 
|---|---:|---:|
| Success | 240 | 19.4% |
| Failure | 1,000 | 80.6% |

|Failure kind | Count | Ratio | 
|---|---:|---:|
| remainder | 780 | 78.0% |
| true divide other | 220 | 22.0% |


</details>

### BINARY_SUBSCR

<details>
<summary> specialization stats for BINARY_SUBSCR family </summary>

|Kind | Count | Ratio | 
|---|---:|---:|
|     deferred | 506,900 | 97.9% |
|          hit | 10,220 | 2.0% |

| | Count | Ratio | 
|---|---:|---:|
| Success | 20 | 3.7% |
| Failure | 520 | 96.3% |

|Failure kind | Count | Ratio | 
|---|---:|---:|
| buffer int | 520 | 100.0% |


</details>

### CALL

<details>
<summary> specialization stats for CALL family </summary>

|Kind | Count | Ratio | 
|---|---:|---:|
|     deferred | 10,528,520 | 6.7% |
|          hit | 145,380,740 | 93.2% |
|         miss | 6,678,380 | 4.3% |

| | Count | Ratio | 
|---|---:|---:|
| Success | 128,260 | 97.4% |
| Failure | 3,420 | 2.6% |

|Failure kind | Count | Ratio | 
|---|---:|---:|
| class mutable | 1,920 | 56.1% |
| operator wrapper | 1,060 | 31.0% |
| wrong number arguments | 260 | 7.6% |
| other | 120 | 3.5% |
| cfunc noargs | 60 | 1.8% |


</details>

### COMPARE_OP

<details>
<summary> specialization stats for COMPARE_OP family </summary>

|Kind | Count | Ratio | 
|---|---:|---:|
|     deferred | 5,509,540 | 5.9% |
|          hit | 87,805,100 | 94.1% |

| | Count | Ratio | 
|---|---:|---:|
| Success | 420 | 14.6% |
| Failure | 2,460 | 85.4% |

|Failure kind | Count | Ratio | 
|---|---:|---:|
| baseobject | 1,720 | 69.9% |
| different types | 620 | 25.2% |
| float long | 120 | 4.9% |


</details>

### FOR_ITER

<details>
<summary> specialization stats for FOR_ITER family </summary>

|Kind | Count | Ratio | 
|---|---:|---:|
|     deferred | 260 | 0.0% |
|          hit | 43,107,660 | 100.0% |

| | Count | Ratio | 
|---|---:|---:|
| Success | 260 | 100.0% |
| Failure | 0 | 0.0% |


</details>

### LOAD_ATTR

<details>
<summary> specialization stats for LOAD_ATTR family </summary>

|Kind | Count | Ratio | 
|---|---:|---:|
|     deferred | 28,241,680 | 5.8% |
|          hit | 457,907,600 | 94.1% |
|         miss | 10,693,360 | 2.2% |

| | Count | Ratio | 
|---|---:|---:|
| Success | 205,280 | 94.7% |
| Failure | 11,440 | 5.3% |

|Failure kind | Count | Ratio | 
|---|---:|---:|
| has managed dict | 4,860 | 42.5% |
| class method obj | 3,440 | 30.1% |
| mutable class | 3,140 | 27.4% |


</details>

### LOAD_GLOBAL

<details>
<summary> specialization stats for LOAD_GLOBAL family </summary>

|Kind | Count | Ratio | 
|---|---:|---:|
|     deferred | 2,040 | 0.0% |
|          hit | 102,341,880 | 100.0% |

| | Count | Ratio | 
|---|---:|---:|
| Success | 2,040 | 100.0% |
| Failure | 0 | 0.0% |


</details>

### LOAD_SUPER_ATTR

<details>
<summary> specialization stats for LOAD_SUPER_ATTR family </summary>

|Kind | Count | Ratio | 
|---|---:|---:|
|     deferred | 220 | 0.0% |
|          hit | 3,402,020 | 100.0% |

| | Count | Ratio | 
|---|---:|---:|
| Success | 220 | 100.0% |
| Failure | 0 | 0.0% |


</details>

### POP_JUMP_IF_FALSE

<details>
<summary> specialization stats for POP_JUMP_IF_FALSE family </summary>


</details>

### POP_JUMP_IF_NONE

<details>
<summary> specialization stats for POP_JUMP_IF_NONE family </summary>


</details>

### POP_JUMP_IF_TRUE

<details>
<summary> specialization stats for POP_JUMP_IF_TRUE family </summary>


</details>

### STORE_ATTR

<details>
<summary> specialization stats for STORE_ATTR family </summary>

|Kind | Count | Ratio | 
|---|---:|---:|
|     deferred | 1,842,980 | 3.3% |
|          hit | 53,212,380 | 96.6% |
|         miss | 1,877,160 | 3.4% |

| | Count | Ratio | 
|---|---:|---:|
| Success | 36,340 | 99.9% |
| Failure | 40 | 0.1% |

|Failure kind | Count | Ratio | 
|---|---:|---:|
| not in keys | 40 | 100.0% |


</details>

### TO_BOOL

<details>
<summary> specialization stats for TO_BOOL family </summary>

|Kind | Count | Ratio | 
|---|---:|---:|
|     deferred | 640 | 0.0% |
|          hit | 22,647,680 | 100.0% |

| | Count | Ratio | 
|---|---:|---:|
| Success | 640 | 100.0% |
| Failure | 0 | 0.0% |


</details>

### UNPACK_SEQUENCE

<details>
<summary> specialization stats for UNPACK_SEQUENCE family </summary>

|Kind | Count | Ratio | 
|---|---:|---:|
|     deferred | 20 | 0.8% |
|          hit | 2,540 | 98.4% |

| | Count | Ratio | 
|---|---:|---:|
| Success | 20 | 100.0% |
| Failure | 0 | 0.0% |


</details>


</details>

## Specialization effectiveness

<details>
<summary> specialization effectiveness </summary>

|Instructions | Count | Ratio | 
|---|---:|---:|
| Basic | 724,048,040 | 37.4% |
| Not specialized | 137,132,360 | 7.1% |
| Specialized hits | 1,054,117,160 | 54.5% |
| Specialized misses | 19,252,460 | 1.0% |

### Deferred by instruction

<details>
<summary> deferred by instruction </summary>

|Name | Count | Ratio | 
|---|---:|---:|
| LOAD_ATTR | 28,241,680 | 59.5% |
| CALL | 10,528,520 | 22.2% |
| COMPARE_OP | 5,509,540 | 11.6% |
| STORE_ATTR | 1,842,980 | 3.9% |
| BINARY_OP | 855,280 | 1.8% |
| BINARY_SUBSCR | 506,900 | 1.1% |
| LOAD_GLOBAL | 2,040 | 0.0% |
| TO_BOOL | 640 | 0.0% |
| FOR_ITER | 260 | 0.0% |
| LOAD_SUPER_ATTR | 220 | 0.0% |


</details>

### Misses by instruction

<details>
<summary> misses by instruction </summary>

|Name | Count | Ratio | 
|---|---:|---:|
| LOAD_ATTR_METHOD_WITH_VALUES | 6,618,100 | 34.4% |
| LOAD_ATTR_INSTANCE_VALUE | 4,075,260 | 21.2% |
| CALL_PY_EXACT_ARGS | 3,482,200 | 18.1% |
| CALL_METHOD_DESCRIPTOR_FAST | 3,185,780 | 16.5% |
| STORE_ATTR_INSTANCE_VALUE | 1,877,160 | 9.7% |
| CALL_METHOD_DESCRIPTOR_O | 10,400 | 0.1% |
| RESUME | 3,560 | 0.0% |
| RESUME_CHECK | 3,560 | 0.0% |
| CACHE | 0 | 0.0% |
| EXIT_INIT_CHECK | 0 | 0.0% |


</details>


</details>

## Call stats

<details>
<summary> Inlined calls and frame stats </summary>

| | Count | Ratio | 
|---|---:|---:|
| Calls to PyEval_EvalDefault | 261,380 | 0.2% |
| Calls to Python functions inlined | 131,376,460 | 99.8% |
| Calls via PyEval_EvalFrame (total) | 261,380 | 0.2% |
| Calls via PyEval_EvalFrame (vector) | 261,380 | 0.2% |
| Calls via PyEval_EvalFrame (generator) | 0 | 0.0% |
| Calls via PyEval_EvalFrame (legacy) | 0 | 0.0% |
| Calls via PyEval_EvalFrame (function vectorcall) | 261,380 | 0.2% |
| Calls via PyEval_EvalFrame (build class) | 0 | 0.0% |
| Calls via PyEval_EvalFrame (slot) | 0 | 0.0% |
| Calls via PyEval_EvalFrame (function ex) | 80 | 0.0% |
| Calls via PyEval_EvalFrame (api) | 0 | 0.0% |
| Calls via PyEval_EvalFrame (method) | 0 | 0.0% |
| Frame objects created | 0 | 0.0% |
| Frames pushed | 129,276,100 | 98.2% |


</details>

## Object stats

<details>
<summary> allocations, frees and dict materializatons </summary>

| | Count | Ratio | 
|---|---:|---:|
| Allocations from freelist | 1,929,960 | 6.6% |
| Frees to freelist | 1,930,240 |  |
| Allocations | 27,356,340 | 93.4% |
| Allocations to 512 bytes | 27,356,340 | 93.4% |
| Allocations to 4 kbytes | 0 | 0.0% |
| Allocations over 4 kbytes | 0 | 0.0% |
| Frees | 29,378,587 |  |
| New values | 258,820 |  |
| Interpreter increfs | 940,277,620 | 93.2% |
| Interpreter decrefs | 985,867,040 | 95.2% |
| Increfs | 68,303,826 | 6.8% |
| Decrefs | 49,696,098 | 4.8% |
| Materialize dict (on request) | 0 | 0.0% |
| Materialize dict (new key) | 0 | 0.0% |
| Materialize dict (too big) | 0 | 0.0% |
| Materialize dict (str subclass) | 0 | 0.0% |
| Dematerialize dict | 0 | 0.0% |
| Method cache hits | 38,927,899 |  |
| Method cache misses | 28,481 |  |
| Method cache collisions | 27,793 |  |
| Method cache dunder hits | 766,904 |  |
| Method cache dunder misses | 196 |  |


</details>

## GC stats

<details>
<summary> GC collections and effectiveness </summary>

|Generation | Collections | Objects collected | Object visits | 
|---:|---:|---:|---:|
| 0 | 3,040 | 600,560 | 23,402,920 |
| 1 | 260 | 1,457,840 | 17,960,000 |
| 2 | 20 | 102,800 | 3,791,720 |


</details>

## Optimization (Tier 2) stats

<details>
<summary> statistics about the Tier 2 optimizer </summary>

| | Count | Ratio | 
|---|---:|---:|
| Optimization attempts | 0 |  |
| Traces created | 0 |  |
| Trace stack overflow | 0 |  |
| Trace stack underflow | 0 |  |
| Trace too long | 0 |  |
| Trace too short | 0 |  |
| Inner loop found | 0 |  |
| Recursive call | 0 |  |
| Low confidence | 0 |  |
| Traces executed | 0 |  |
| Uops executed | 0 |  |

### Trace length histogram

<details>
<summary> trace length histogram </summary>

|Range | Count | Ratio | 
|---|---:|---:|
| <= 1 | 0 |  |


</details>

### Optimized trace length histogram

<details>
<summary> optimized trace length histogram </summary>

|Range | Count | Ratio | 
|---|---:|---:|
| <= 1 | 0 |  |


</details>

### Trace run length histogram

<details>
<summary> trace run length histogram </summary>

|Range | Count | Ratio | 
|---|---:|---:|
| <= 1 | 0 |  |


</details>

### Uop execution stats

<details>
<summary> uop execution stats </summary>


</details>

### Unsupported opcodes

<details>
<summary> unsupported opcodes </summary>


</details>


</details>

## Rare events

<details>
<summary> Counts of rare/unlikely events </summary>

|Event | Count | 
|---|---:|
| set class | 0 |
| set bases | 0 |
| set eval frame func | 0 |
| builtin dict | 0 |
| func modification | 0 |
| watched dict modification | 0 |
| watched globals modification | 0 |


</details>

## Meta stats

<details>
<summary> Meta statistics </summary>

| | Count | 
|---|---:|
| Number of data files | 20 |


</details>

---
Stats gathered on: 2024-09-10
